{
  "userProfilePK": 131621693,
  "calendarDate": "2026-06-05",
  "startTimestampGMT": "2026-06-05T03:00:00.0",
  "endTimestampGMT": "2026-06-06T03:00:00.0",
  "startTimestampLocal": "2026-06-05T00:00:00.0",
  "endTimestampLocal": "2026-06-06T00:00:00.0",
  "maxStressLevel": 96,
  "avgStressLevel": 29,
  "stressChartValueOffset": 1,
  "stressChartYAxisOrigin": -1,
  "stressValueDescriptorsDTOList": [
    {
      "index": 0,
      "key": "timestamp"
    },
    {
      "index": 1,
      "key": "stressLevel"
    }
  ],
  "stressValuesArray": [
    [
      1780628400000,
      25
    ],
    [
      1780628580000,
      16
    ],
    [
      1780628760000,
      16
    ],
    [
      1780628940000,
      11
    ],
    [
      1780629120000,
      13
    ],
    [
      1780629300000,
      13
    ],
    [
      1780629480000,
      11
    ],
    [
      1780629660000,
      14
    ],
    [
      1780629840000,
      15
    ],
    [
      1780630020000,
      12
    ],
    [
      1780630200000,
      15
    ],
    [
      1780630380000,
      11
    ],
    [
      1780630560000,
      12
    ],
    [
      1780630740000,
      15
    ],
    [
      1780630920000,
      18
    ],
    [
      1780631100000,
      15
    ],
    [
      1780631280000,
      16
    ],
    [
      1780631460000,
      13
    ],
    [
      1780631640000,
      13
    ],
    [
      1780631820000,
      10
    ],
    [
      1780632000000,
      11
    ],
    [
      1780632180000,
      13
    ],
    [
      1780632360000,
      9
    ],
    [
      1780632540000,
      8
    ],
    [
      1780632720000,
      22
    ],
    [
      1780632900000,
      10
    ],
    [
      1780633080000,
      9
    ],
    [
      1780633260000,
      10
    ],
    [
      1780633440000,
      11
    ],
    [
      1780633620000,
      11
    ],
    [
      1780633800000,
      17
    ],
    [
      1780633980000,
      29
    ],
    [
      1780634160000,
      22
    ],
    [
      1780634340000,
      25
    ],
    [
      1780634520000,
      21
    ],
    [
      1780634700000,
      15
    ],
    [
      1780634880000,
      15
    ],
    [
      1780635060000,
      17
    ],
    [
      1780635240000,
      16
    ],
    [
      1780635420000,
      15
    ],
    [
      1780635600000,
      8
    ],
    [
      1780635780000,
      5
    ],
    [
      1780635960000,
      5
    ],
    [
      1780636140000,
      9
    ],
    [
      1780636320000,
      13
    ],
    [
      1780636500000,
      9
    ],
    [
      1780636680000,
      9
    ],
    [
      1780636860000,
      6
    ],
    [
      1780637040000,
      7
    ],
    [
      1780637220000,
      8
    ],
    [
      1780637400000,
      10
    ],
    [
      1780637580000,
      9
    ],
    [
      1780637760000,
      11
    ],
    [
      1780637940000,
      15
    ],
    [
      1780638120000,
      18
    ],
    [
      1780638300000,
      10
    ],
    [
      1780638480000,
      14
    ],
    [
      1780638660000,
      17
    ],
    [
      1780638840000,
      12
    ],
    [
      1780639020000,
      12
    ],
    [
      1780639200000,
      12
    ],
    [
      1780639380000,
      9
    ],
    [
      1780639560000,
      5
    ],
    [
      1780639740000,
      8
    ],
    [
      1780639920000,
      23
    ],
    [
      1780640100000,
      14
    ],
    [
      1780640280000,
      15
    ],
    [
      1780640460000,
      15
    ],
    [
      1780640640000,
      14
    ],
    [
      1780640820000,
      11
    ],
    [
      1780641000000,
      8
    ],
    [
      1780641180000,
      7
    ],
    [
      1780641360000,
      9
    ],
    [
      1780641540000,
      9
    ],
    [
      1780641720000,
      13
    ],
    [
      1780641900000,
      15
    ],
    [
      1780642080000,
      14
    ],
    [
      1780642260000,
      7
    ],
    [
      1780642440000,
      5
    ],
    [
      1780642620000,
      9
    ],
    [
      1780642800000,
      10
    ],
    [
      1780642980000,
      4
    ],
    [
      1780643160000,
      5
    ],
    [
      1780643340000,
      5
    ],
    [
      1780643520000,
      5
    ],
    [
      1780643700000,
      8
    ],
    [
      1780643880000,
      6
    ],
    [
      1780644060000,
      8
    ],
    [
      1780644240000,
      12
    ],
    [
      1780644420000,
      18
    ],
    [
      1780644600000,
      7
    ],
    [
      1780644780000,
      8
    ],
    [
      1780644960000,
      10
    ],
    [
      1780645140000,
      12
    ],
    [
      1780645320000,
      10
    ],
    [
      1780645500000,
      10
    ],
    [
      1780645680000,
      15
    ],
    [
      1780645860000,
      14
    ],
    [
      1780646040000,
      11
    ],
    [
      1780646220000,
      12
    ],
    [
      1780646400000,
      18
    ],
    [
      1780646580000,
      16
    ],
    [
      1780646760000,
      15
    ],
    [
      1780646940000,
      14
    ],
    [
      1780647120000,
      10
    ],
    [
      1780647300000,
      13
    ],
    [
      1780647480000,
      14
    ],
    [
      1780647660000,
      21
    ],
    [
      1780647840000,
      16
    ],
    [
      1780648020000,
      18
    ],
    [
      1780648200000,
      12
    ],
    [
      1780648380000,
      14
    ],
    [
      1780648560000,
      12
    ],
    [
      1780648740000,
      11
    ],
    [
      1780648920000,
      15
    ],
    [
      1780649100000,
      11
    ],
    [
      1780649280000,
      16
    ],
    [
      1780649460000,
      17
    ],
    [
      1780649640000,
      10
    ],
    [
      1780649820000,
      13
    ],
    [
      1780650000000,
      15
    ],
    [
      1780650180000,
      4
    ],
    [
      1780650360000,
      19
    ],
    [
      1780650540000,
      13
    ],
    [
      1780650720000,
      14
    ],
    [
      1780650900000,
      13
    ],
    [
      1780651080000,
      15
    ],
    [
      1780651260000,
      8
    ],
    [
      1780651440000,
      14
    ],
    [
      1780651620000,
      17
    ],
    [
      1780651800000,
      -1
    ],
    [
      1780651980000,
      -1
    ],
    [
      1780652160000,
      -1
    ],
    [
      1780652340000,
      -1
    ],
    [
      1780652520000,
      18
    ],
    [
      1780652700000,
      -2
    ],
    [
      1780652880000,
      -1
    ],
    [
      1780653060000,
      -1
    ],
    [
      1780653240000,
      43
    ],
    [
      1780653420000,
      -1
    ],
    [
      1780653600000,
      -1
    ],
    [
      1780653780000,
      -2
    ],
    [
      1780653960000,
      -2
    ],
    [
      1780654140000,
      -2
    ],
    [
      1780654320000,
      -2
    ],
    [
      1780654500000,
      -2
    ],
    [
      1780654680000,
      -2
    ],
    [
      1780654860000,
      -2
    ],
    [
      1780655040000,
      -1
    ],
    [
      1780655220000,
      -2
    ],
    [
      1780655400000,
      -2
    ],
    [
      1780655580000,
      -2
    ],
    [
      1780655760000,
      -2
    ],
    [
      1780655940000,
      -2
    ],
    [
      1780656120000,
      -1
    ],
    [
      1780656300000,
      -2
    ],
    [
      1780656480000,
      -1
    ],
    [
      1780656660000,
      -1
    ],
    [
      1780656840000,
      -2
    ],
    [
      1780657020000,
      -2
    ],
    [
      1780657200000,
      -2
    ],
    [
      1780657380000,
      -2
    ],
    [
      1780657560000,
      -2
    ],
    [
      1780657740000,
      -2
    ],
    [
      1780657920000,
      -2
    ],
    [
      1780658100000,
      -1
    ],
    [
      1780658280000,
      -1
    ],
    [
      1780658460000,
      -1
    ],
    [
      1780658640000,
      -2
    ],
    [
      1780658820000,
      -1
    ],
    [
      1780659000000,
      -1
    ],
    [
      1780659180000,
      -1
    ],
    [
      1780659360000,
      -1
    ],
    [
      1780659540000,
      -2
    ],
    [
      1780659720000,
      -1
    ],
    [
      1780659900000,
      -1
    ],
    [
      1780660080000,
      -1
    ],
    [
      1780660260000,
      69
    ],
    [
      1780660440000,
      -1
    ],
    [
      1780660620000,
      52
    ],
    [
      1780660800000,
      73
    ],
    [
      1780660980000,
      54
    ],
    [
      1780661160000,
      68
    ],
    [
      1780661340000,
      72
    ],
    [
      1780661520000,
      -1
    ],
    [
      1780661700000,
      -2
    ],
    [
      1780661880000,
      -2
    ],
    [
      1780662060000,
      -2
    ],
    [
      1780662240000,
      -1
    ],
    [
      1780662420000,
      -1
    ],
    [
      1780662600000,
      -1
    ],
    [
      1780662780000,
      80
    ],
    [
      1780662960000,
      -1
    ],
    [
      1780663140000,
      -1
    ],
    [
      1780663320000,
      95
    ],
    [
      1780663500000,
      -1
    ],
    [
      1780663680000,
      73
    ],
    [
      1780663860000,
      74
    ],
    [
      1780664040000,
      71
    ],
    [
      1780664220000,
      79
    ],
    [
      1780664400000,
      64
    ],
    [
      1780664580000,
      73
    ],
    [
      1780664760000,
      73
    ],
    [
      1780664940000,
      85
    ],
    [
      1780665120000,
      84
    ],
    [
      1780665300000,
      83
    ],
    [
      1780665480000,
      66
    ],
    [
      1780665660000,
      72
    ],
    [
      1780665840000,
      74
    ],
    [
      1780666020000,
      76
    ],
    [
      1780666200000,
      82
    ],
    [
      1780666380000,
      79
    ],
    [
      1780666560000,
      78
    ],
    [
      1780666740000,
      -1
    ],
    [
      1780666920000,
      74
    ],
    [
      1780667100000,
      88
    ],
    [
      1780667280000,
      42
    ],
    [
      1780667460000,
      37
    ],
    [
      1780667640000,
      35
    ],
    [
      1780667820000,
      46
    ],
    [
      1780668000000,
      35
    ],
    [
      1780668180000,
      43
    ],
    [
      1780668360000,
      -2
    ],
    [
      1780668540000,
      -1
    ],
    [
      1780668720000,
      -1
    ],
    [
      1780668900000,
      43
    ],
    [
      1780669080000,
      47
    ],
    [
      1780669260000,
      61
    ],
    [
      1780669440000,
      57
    ],
    [
      1780669620000,
      67
    ],
    [
      1780669800000,
      60
    ],
    [
      1780669980000,
      49
    ],
    [
      1780670160000,
      58
    ],
    [
      1780670340000,
      40
    ],
    [
      1780670520000,
      45
    ],
    [
      1780670700000,
      62
    ],
    [
      1780670880000,
      52
    ],
    [
      1780671060000,
      27
    ],
    [
      1780671240000,
      25
    ],
    [
      1780671420000,
      52
    ],
    [
      1780671600000,
      -1
    ],
    [
      1780671780000,
      -1
    ],
    [
      1780671960000,
      37
    ],
    [
      1780672140000,
      61
    ],
    [
      1780672320000,
      64
    ],
    [
      1780672500000,
      58
    ],
    [
      1780672680000,
      56
    ],
    [
      1780672860000,
      56
    ],
    [
      1780673040000,
      34
    ],
    [
      1780673220000,
      41
    ],
    [
      1780673400000,
      47
    ],
    [
      1780673580000,
      28
    ],
    [
      1780673760000,
      39
    ],
    [
      1780673940000,
      44
    ],
    [
      1780674120000,
      38
    ],
    [
      1780674300000,
      38
    ],
    [
      1780674480000,
      31
    ],
    [
      1780674660000,
      33
    ],
    [
      1780674840000,
      37
    ],
    [
      1780675020000,
      28
    ],
    [
      1780675200000,
      43
    ],
    [
      1780675380000,
      32
    ],
    [
      1780675560000,
      35
    ],
    [
      1780675740000,
      27
    ],
    [
      1780675920000,
      37
    ],
    [
      1780676100000,
      30
    ],
    [
      1780676280000,
      58
    ],
    [
      1780676460000,
      -1
    ],
    [
      1780676640000,
      -1
    ],
    [
      1780676820000,
      -1
    ],
    [
      1780677000000,
      -2
    ],
    [
      1780677180000,
      45
    ],
    [
      1780677360000,
      52
    ],
    [
      1780677540000,
      54
    ],
    [
      1780677720000,
      -2
    ],
    [
      1780677900000,
      -2
    ],
    [
      1780678080000,
      -2
    ],
    [
      1780678260000,
      34
    ],
    [
      1780678440000,
      51
    ],
    [
      1780678620000,
      43
    ],
    [
      1780678800000,
      50
    ],
    [
      1780678980000,
      56
    ],
    [
      1780679160000,
      64
    ],
    [
      1780679340000,
      58
    ],
    [
      1780679520000,
      60
    ],
    [
      1780679700000,
      59
    ],
    [
      1780679880000,
      53
    ],
    [
      1780680060000,
      -1
    ],
    [
      1780690860000,
      -1
    ],
    [
      1780691040000,
      -1
    ],
    [
      1780691220000,
      34
    ],
    [
      1780691400000,
      25
    ],
    [
      1780691580000,
      -1
    ],
    [
      1780691760000,
      -1
    ],
    [
      1780691940000,
      -1
    ],
    [
      1780692120000,
      -1
    ],
    [
      1780692300000,
      -2
    ],
    [
      1780692480000,
      64
    ],
    [
      1780692660000,
      -2
    ],
    [
      1780692840000,
      -2
    ],
    [
      1780693020000,
      -2
    ],
    [
      1780693200000,
      -1
    ],
    [
      1780693380000,
      -2
    ],
    [
      1780693560000,
      -2
    ],
    [
      1780693740000,
      -2
    ],
    [
      1780693920000,
      -1
    ],
    [
      1780694100000,
      -1
    ],
    [
      1780694280000,
      -2
    ],
    [
      1780694460000,
      -2
    ],
    [
      1780694640000,
      -1
    ],
    [
      1780694820000,
      -1
    ],
    [
      1780695000000,
      -1
    ],
    [
      1780695180000,
      25
    ],
    [
      1780695360000,
      33
    ],
    [
      1780695540000,
      37
    ],
    [
      1780695720000,
      -2
    ],
    [
      1780695900000,
      -2
    ],
    [
      1780696080000,
      -1
    ],
    [
      1780696260000,
      -1
    ],
    [
      1780696440000,
      -1
    ],
    [
      1780696620000,
      -2
    ],
    [
      1780696800000,
      -2
    ],
    [
      1780696980000,
      36
    ],
    [
      1780697160000,
      65
    ],
    [
      1780697340000,
      52
    ],
    [
      1780697520000,
      34
    ],
    [
      1780697700000,
      46
    ],
    [
      1780697880000,
      31
    ],
    [
      1780698060000,
      43
    ],
    [
      1780698240000,
      27
    ],
    [
      1780698420000,
      37
    ],
    [
      1780698600000,
      42
    ],
    [
      1780698780000,
      53
    ],
    [
      1780698960000,
      43
    ],
    [
      1780699140000,
      47
    ],
    [
      1780699320000,
      46
    ],
    [
      1780699500000,
      33
    ],
    [
      1780699680000,
      31
    ],
    [
      1780699860000,
      39
    ],
    [
      1780700040000,
      39
    ],
    [
      1780700220000,
      43
    ],
    [
      1780700400000,
      25
    ],
    [
      1780700580000,
      29
    ],
    [
      1780700760000,
      42
    ],
    [
      1780700940000,
      31
    ],
    [
      1780701120000,
      33
    ],
    [
      1780701300000,
      35
    ],
    [
      1780701480000,
      31
    ],
    [
      1780701660000,
      25
    ],
    [
      1780701840000,
      34
    ],
    [
      1780702020000,
      35
    ],
    [
      1780702200000,
      34
    ],
    [
      1780702380000,
      33
    ],
    [
      1780702560000,
      25
    ],
    [
      1780702740000,
      37
    ],
    [
      1780702920000,
      34
    ],
    [
      1780703100000,
      -1
    ],
    [
      1780703280000,
      36
    ],
    [
      1780703460000,
      34
    ],
    [
      1780703640000,
      33
    ],
    [
      1780703820000,
      43
    ],
    [
      1780704000000,
      34
    ],
    [
      1780704180000,
      25
    ],
    [
      1780704360000,
      23
    ],
    [
      1780704540000,
      25
    ],
    [
      1780704720000,
      24
    ],
    [
      1780704900000,
      25
    ],
    [
      1780705080000,
      25
    ],
    [
      1780705260000,
      28
    ],
    [
      1780705440000,
      28
    ],
    [
      1780705620000,
      23
    ],
    [
      1780705800000,
      24
    ],
    [
      1780705980000,
      24
    ],
    [
      1780706160000,
      25
    ],
    [
      1780706340000,
      25
    ],
    [
      1780706520000,
      25
    ],
    [
      1780706700000,
      20
    ],
    [
      1780706880000,
      24
    ],
    [
      1780707060000,
      20
    ],
    [
      1780707240000,
      25
    ],
    [
      1780707420000,
      24
    ],
    [
      1780707600000,
      18
    ],
    [
      1780707780000,
      -1
    ],
    [
      1780707960000,
      -1
    ],
    [
      1780708140000,
      23
    ],
    [
      1780708320000,
      17
    ],
    [
      1780708500000,
      10
    ],
    [
      1780708680000,
      20
    ],
    [
      1780708860000,
      10
    ],
    [
      1780709040000,
      9
    ],
    [
      1780709220000,
      12
    ],
    [
      1780709400000,
      14
    ],
    [
      1780709580000,
      15
    ],
    [
      1780709760000,
      14
    ],
    [
      1780709940000,
      13
    ],
    [
      1780710120000,
      15
    ],
    [
      1780710300000,
      10
    ],
    [
      1780710480000,
      17
    ],
    [
      1780710660000,
      10
    ],
    [
      1780710840000,
      15
    ],
    [
      1780711020000,
      12
    ],
    [
      1780711200000,
      14
    ],
    [
      1780711380000,
      11
    ],
    [
      1780711560000,
      13
    ],
    [
      1780711740000,
      16
    ],
    [
      1780711920000,
      16
    ],
    [
      1780712100000,
      18
    ],
    [
      1780712280000,
      13
    ],
    [
      1780712460000,
      18
    ],
    [
      1780712640000,
      15
    ],
    [
      1780712820000,
      17
    ],
    [
      1780713000000,
      19
    ],
    [
      1780713180000,
      18
    ],
    [
      1780713360000,
      25
    ],
    [
      1780713540000,
      25
    ],
    [
      1780713720000,
      26
    ],
    [
      1780713900000,
      24
    ],
    [
      1780714080000,
      18
    ],
    [
      1780714260000,
      15
    ],
    [
      1780714440000,
      15
    ],
    [
      1780714620000,
      13
    ]
  ],
  "bodyBatteryValueDescriptorsDTOList": [
    {
      "bodyBatteryValueDescriptorIndex": 0,
      "bodyBatteryValueDescriptorKey": "timestamp"
    },
    {
      "bodyBatteryValueDescriptorIndex": 1,
      "bodyBatteryValueDescriptorKey": "bodyBatteryStatus"
    },
    {
      "bodyBatteryValueDescriptorIndex": 2,
      "bodyBatteryValueDescriptorKey": "bodyBatteryLevel"
    },
    {
      "bodyBatteryValueDescriptorIndex": 3,
      "bodyBatteryValueDescriptorKey": "bodyBatteryVersion"
    }
  ],
  "bodyBatteryValuesArray": [
    [
      1780628400000,
      "MEASURED",
      36,
      3.0
    ],
    [
      1780628580000,
      "MEASURED",
      36,
      3.0
    ],
    [
      1780628760000,
      "MEASURED",
      36,
      3.0
    ],
    [
      1780628940000,
      "MEASURED",
      36,
      3.0
    ],
    [
      1780629120000,
      "MEASURED",
      37,
      3.0
    ],
    [
      1780629300000,
      "MEASURED",
      37,
      3.0
    ],
    [
      1780629480000,
      "MEASURED",
      37,
      3.0
    ],
    [
      1780629660000,
      "MEASURED",
      38,
      3.0
    ],
    [
      1780629840000,
      "MEASURED",
      38,
      3.0
    ],
    [
      1780630020000,
      "MEASURED",
      39,
      3.0
    ],
    [
      1780630200000,
      "MEASURED",
      40,
      3.0
    ],
    [
      1780630380000,
      "MEASURED",
      40,
      3.0
    ],
    [
      1780630560000,
      "MEASURED",
      40,
      3.0
    ],
    [
      1780630740000,
      "MEASURED",
      41,
      3.0
    ],
    [
      1780630920000,
      "MEASURED",
      42,
      3.0
    ],
    [
      1780631100000,
      "MEASURED",
      42,
      3.0
    ],
    [
      1780631280000,
      "MEASURED",
      42,
      3.0
    ],
    [
      1780631460000,
      "MEASURED",
      43,
      3.0
    ],
    [
      1780631640000,
      "MEASURED",
      43,
      3.0
    ],
    [
      1780631820000,
      "MEASURED",
      44,
      3.0
    ],
    [
      1780632000000,
      "MEASURED",
      44,
      3.0
    ],
    [
      1780632180000,
      "MEASURED",
      45,
      3.0
    ],
    [
      1780632360000,
      "MEASURED",
      46,
      3.0
    ],
    [
      1780632540000,
      "MEASURED",
      46,
      3.0
    ],
    [
      1780632720000,
      "MEASURED",
      47,
      3.0
    ],
    [
      1780632900000,
      "MEASURED",
      47,
      3.0
    ],
    [
      1780633080000,
      "MEASURED",
      47,
      3.0
    ],
    [
      1780633260000,
      "MEASURED",
      47,
      3.0
    ],
    [
      1780633440000,
      "MEASURED",
      48,
      3.0
    ],
    [
      1780633620000,
      "MEASURED",
      48,
      3.0
    ],
    [
      1780633800000,
      "MEASURED",
      48,
      3.0
    ],
    [
      1780633980000,
      "MEASURED",
      49,
      3.0
    ],
    [
      1780634160000,
      "MEASURED",
      49,
      3.0
    ],
    [
      1780634340000,
      "MEASURED",
      50,
      3.0
    ],
    [
      1780634520000,
      "MEASURED",
      50,
      3.0
    ],
    [
      1780634700000,
      "MEASURED",
      51,
      3.0
    ],
    [
      1780634880000,
      "MEASURED",
      51,
      3.0
    ],
    [
      1780635060000,
      "MEASURED",
      52,
      3.0
    ],
    [
      1780635240000,
      "MEASURED",
      53,
      3.0
    ],
    [
      1780635420000,
      "MEASURED",
      54,
      3.0
    ],
    [
      1780635600000,
      "MEASURED",
      54,
      3.0
    ],
    [
      1780635780000,
      "MEASURED",
      55,
      3.0
    ],
    [
      1780635960000,
      "MEASURED",
      56,
      3.0
    ],
    [
      1780636140000,
      "MEASURED",
      56,
      3.0
    ],
    [
      1780636320000,
      "MEASURED",
      57,
      3.0
    ],
    [
      1780636500000,
      "MEASURED",
      58,
      3.0
    ],
    [
      1780636680000,
      "MEASURED",
      58,
      3.0
    ],
    [
      1780636860000,
      "MEASURED",
      59,
      3.0
    ],
    [
      1780637040000,
      "MEASURED",
      59,
      3.0
    ],
    [
      1780637220000,
      "MEASURED",
      60,
      3.0
    ],
    [
      1780637400000,
      "MEASURED",
      60,
      3.0
    ],
    [
      1780637580000,
      "MEASURED",
      61,
      3.0
    ],
    [
      1780637760000,
      "MEASURED",
      62,
      3.0
    ],
    [
      1780637940000,
      "MEASURED",
      62,
      3.0
    ],
    [
      1780638120000,
      "MEASURED",
      63,
      3.0
    ],
    [
      1780638300000,
      "MEASURED",
      63,
      3.0
    ],
    [
      1780638480000,
      "MEASURED",
      63,
      3.0
    ],
    [
      1780638660000,
      "MEASURED",
      63,
      3.0
    ],
    [
      1780638840000,
      "MEASURED",
      65,
      3.0
    ],
    [
      1780639020000,
      "MEASURED",
      65,
      3.0
    ],
    [
      1780639200000,
      "MEASURED",
      65,
      3.0
    ],
    [
      1780639380000,
      "MEASURED",
      66,
      3.0
    ],
    [
      1780639560000,
      "MEASURED",
      66,
      3.0
    ],
    [
      1780639740000,
      "MEASURED",
      67,
      3.0
    ],
    [
      1780639920000,
      "MEASURED",
      68,
      3.0
    ],
    [
      1780640100000,
      "MEASURED",
      68,
      3.0
    ],
    [
      1780640280000,
      "MEASURED",
      69,
      3.0
    ],
    [
      1780640460000,
      "MEASURED",
      69,
      3.0
    ],
    [
      1780640640000,
      "MEASURED",
      69,
      3.0
    ],
    [
      1780640820000,
      "MEASURED",
      70,
      3.0
    ],
    [
      1780641000000,
      "MEASURED",
      70,
      3.0
    ],
    [
      1780641180000,
      "MEASURED",
      71,
      3.0
    ],
    [
      1780641360000,
      "MEASURED",
      71,
      3.0
    ],
    [
      1780641540000,
      "MEASURED",
      72,
      3.0
    ],
    [
      1780641720000,
      "MEASURED",
      72,
      3.0
    ],
    [
      1780641900000,
      "MEASURED",
      73,
      3.0
    ],
    [
      1780642080000,
      "MEASURED",
      73,
      3.0
    ],
    [
      1780642260000,
      "MEASURED",
      73,
      3.0
    ],
    [
      1780642440000,
      "MEASURED",
      74,
      3.0
    ],
    [
      1780642620000,
      "MEASURED",
      75,
      3.0
    ],
    [
      1780642800000,
      "MEASURED",
      76,
      3.0
    ],
    [
      1780642980000,
      "MEASURED",
      76,
      3.0
    ],
    [
      1780643160000,
      "MEASURED",
      76,
      3.0
    ],
    [
      1780643340000,
      "MEASURED",
      77,
      3.0
    ],
    [
      1780643520000,
      "MEASURED",
      77,
      3.0
    ],
    [
      1780643700000,
      "MEASURED",
      78,
      3.0
    ],
    [
      1780643880000,
      "MEASURED",
      79,
      3.0
    ],
    [
      1780644060000,
      "MEASURED",
      79,
      3.0
    ],
    [
      1780644240000,
      "MEASURED",
      80,
      3.0
    ],
    [
      1780644420000,
      "MEASURED",
      80,
      3.0
    ],
    [
      1780644600000,
      "MEASURED",
      80,
      3.0
    ],
    [
      1780644780000,
      "MEASURED",
      81,
      3.0
    ],
    [
      1780644960000,
      "MEASURED",
      81,
      3.0
    ],
    [
      1780645140000,
      "MEASURED",
      81,
      3.0
    ],
    [
      1780645320000,
      "MEASURED",
      82,
      3.0
    ],
    [
      1780645500000,
      "MEASURED",
      82,
      3.0
    ],
    [
      1780645680000,
      "MEASURED",
      83,
      3.0
    ],
    [
      1780645860000,
      "MEASURED",
      83,
      3.0
    ],
    [
      1780646040000,
      "MEASURED",
      83,
      3.0
    ],
    [
      1780646220000,
      "MEASURED",
      84,
      3.0
    ],
    [
      1780646400000,
      "MEASURED",
      84,
      3.0
    ],
    [
      1780646580000,
      "MEASURED",
      84,
      3.0
    ],
    [
      1780646760000,
      "MEASURED",
      85,
      3.0
    ],
    [
      1780646940000,
      "MEASURED",
      85,
      3.0
    ],
    [
      1780647120000,
      "MEASURED",
      85,
      3.0
    ],
    [
      1780647300000,
      "MEASURED",
      85,
      3.0
    ],
    [
      1780647480000,
      "MEASURED",
      86,
      3.0
    ],
    [
      1780647660000,
      "MEASURED",
      86,
      3.0
    ],
    [
      1780647840000,
      "MEASURED",
      87,
      3.0
    ],
    [
      1780648020000,
      "MEASURED",
      87,
      3.0
    ],
    [
      1780648200000,
      "MEASURED",
      87,
      3.0
    ],
    [
      1780648380000,
      "MEASURED",
      87,
      3.0
    ],
    [
      1780648560000,
      "MEASURED",
      87,
      3.0
    ],
    [
      1780648740000,
      "MEASURED",
      87,
      3.0
    ],
    [
      1780648920000,
      "MEASURED",
      87,
      3.0
    ],
    [
      1780649100000,
      "MEASURED",
      88,
      3.0
    ],
    [
      1780649280000,
      "MEASURED",
      89,
      3.0
    ],
    [
      1780649460000,
      "MEASURED",
      89,
      3.0
    ],
    [
      1780649640000,
      "MEASURED",
      89,
      3.0
    ],
    [
      1780649820000,
      "MEASURED",
      89,
      3.0
    ],
    [
      1780650000000,
      "MEASURED",
      89,
      3.0
    ],
    [
      1780650180000,
      "MEASURED",
      90,
      3.0
    ],
    [
      1780650360000,
      "MEASURED",
      90,
      3.0
    ],
    [
      1780650540000,
      "MEASURED",
      90,
      3.0
    ],
    [
      1780650720000,
      "MEASURED",
      91,
      3.0
    ],
    [
      1780650900000,
      "MEASURED",
      91,
      3.0
    ],
    [
      1780651080000,
      "MEASURED",
      91,
      3.0
    ],
    [
      1780651260000,
      "MEASURED",
      91,
      3.0
    ],
    [
      1780651440000,
      "MEASURED",
      92,
      3.0
    ],
    [
      1780651620000,
      "MEASURED",
      92,
      3.0
    ],
    [
      1780651800000,
      "MEASURED",
      92,
      3.0
    ],
    [
      1780651980000,
      "MEASURED",
      92,
      3.0
    ],
    [
      1780652160000,
      "MEASURED",
      91,
      3.0
    ],
    [
      1780652340000,
      "MEASURED",
      91,
      3.0
    ],
    [
      1780652520000,
      "MEASURED",
      91,
      3.0
    ],
    [
      1780652700000,
      "MEASURED",
      90,
      3.0
    ],
    [
      1780652880000,
      "MEASURED",
      90,
      3.0
    ],
    [
      1780653060000,
      "MEASURED",
      90,
      3.0
    ],
    [
      1780653240000,
      "MEASURED",
      89,
      3.0
    ],
    [
      1780653420000,
      "MEASURED",
      89,
      3.0
    ],
    [
      1780653600000,
      "MEASURED",
      89,
      3.0
    ],
    [
      1780653780000,
      "MEASURED",
      88,
      3.0
    ],
    [
      1780653960000,
      "MEASURED",
      88,
      3.0
    ],
    [
      1780654140000,
      "MEASURED",
      88,
      3.0
    ],
    [
      1780654320000,
      "MEASURED",
      87,
      3.0
    ],
    [
      1780654500000,
      "MEASURED",
      86,
      3.0
    ],
    [
      1780654680000,
      "MEASURED",
      86,
      3.0
    ],
    [
      1780654860000,
      "MEASURED",
      85,
      3.0
    ],
    [
      1780655040000,
      "MEASURED",
      84,
      3.0
    ],
    [
      1780655220000,
      "MEASURED",
      84,
      3.0
    ],
    [
      1780655400000,
      "MEASURED",
      83,
      3.0
    ],
    [
      1780655580000,
      "MEASURED",
      82,
      3.0
    ],
    [
      1780655760000,
      "MEASURED",
      82,
      3.0
    ],
    [
      1780655940000,
      "MEASURED",
      81,
      3.0
    ],
    [
      1780656120000,
      "MEASURED",
      80,
      3.0
    ],
    [
      1780656300000,
      "MEASURED",
      80,
      3.0
    ],
    [
      1780656480000,
      "MEASURED",
      79,
      3.0
    ],
    [
      1780656660000,
      "MEASURED",
      79,
      3.0
    ],
    [
      1780656840000,
      "MEASURED",
      78,
      3.0
    ],
    [
      1780657020000,
      "MEASURED",
      78,
      3.0
    ],
    [
      1780657200000,
      "MEASURED",
      77,
      3.0
    ],
    [
      1780657380000,
      "MEASURED",
      77,
      3.0
    ],
    [
      1780657560000,
      "MEASURED",
      77,
      3.0
    ],
    [
      1780657740000,
      "MEASURED",
      77,
      3.0
    ],
    [
      1780657920000,
      "RESET",
      77,
      3.0
    ],
    [
      1780658100000,
      "MEASURED",
      77,
      3.0
    ],
    [
      1780658280000,
      "MEASURED",
      76,
      3.0
    ],
    [
      1780658460000,
      "MEASURED",
      76,
      3.0
    ],
    [
      1780658640000,
      "MEASURED",
      76,
      3.0
    ],
    [
      1780658820000,
      "MEASURED",
      75,
      3.0
    ],
    [
      1780659000000,
      "MEASURED",
      75,
      3.0
    ],
    [
      1780659180000,
      "MEASURED",
      74,
      3.0
    ],
    [
      1780659360000,
      "MEASURED",
      74,
      3.0
    ],
    [
      1780659540000,
      "MEASURED",
      73,
      3.0
    ],
    [
      1780659720000,
      "MEASURED",
      73,
      3.0
    ],
    [
      1780659900000,
      "MEASURED",
      73,
      3.0
    ],
    [
      1780660080000,
      "MEASURED",
      72,
      3.0
    ],
    [
      1780660260000,
      "MEASURED",
      72,
      3.0
    ],
    [
      1780660440000,
      "MEASURED",
      72,
      3.0
    ],
    [
      1780660620000,
      "MEASURED",
      71,
      3.0
    ],
    [
      1780660800000,
      "MEASURED",
      71,
      3.0
    ],
    [
      1780660980000,
      "MEASURED",
      70,
      3.0
    ],
    [
      1780661160000,
      "MEASURED",
      70,
      3.0
    ],
    [
      1780661340000,
      "MEASURED",
      69,
      3.0
    ],
    [
      1780661520000,
      "MEASURED",
      69,
      3.0
    ],
    [
      1780661700000,
      "MEASURED",
      69,
      3.0
    ],
    [
      1780661880000,
      "MEASURED",
      68,
      3.0
    ],
    [
      1780662060000,
      "MEASURED",
      68,
      3.0
    ],
    [
      1780662240000,
      "MEASURED",
      68,
      3.0
    ],
    [
      1780662420000,
      "MEASURED",
      68,
      3.0
    ],
    [
      1780662600000,
      "MEASURED",
      67,
      3.0
    ],
    [
      1780662780000,
      "MEASURED",
      67,
      3.0
    ],
    [
      1780662960000,
      "MEASURED",
      66,
      3.0
    ],
    [
      1780663140000,
      "MEASURED",
      66,
      3.0
    ],
    [
      1780663320000,
      "MEASURED",
      65,
      3.0
    ],
    [
      1780663500000,
      "MEASURED",
      65,
      3.0
    ],
    [
      1780663680000,
      "MEASURED",
      65,
      3.0
    ],
    [
      1780663860000,
      "MEASURED",
      64,
      3.0
    ],
    [
      1780664040000,
      "MEASURED",
      64,
      3.0
    ],
    [
      1780664220000,
      "MEASURED",
      63,
      3.0
    ],
    [
      1780664400000,
      "MEASURED",
      62,
      3.0
    ],
    [
      1780664580000,
      "MEASURED",
      62,
      3.0
    ],
    [
      1780664760000,
      "MEASURED",
      61,
      3.0
    ],
    [
      1780664940000,
      "MEASURED",
      61,
      3.0
    ],
    [
      1780665120000,
      "MEASURED",
      60,
      3.0
    ],
    [
      1780665300000,
      "MEASURED",
      60,
      3.0
    ],
    [
      1780665480000,
      "MEASURED",
      59,
      3.0
    ],
    [
      1780665660000,
      "MEASURED",
      59,
      3.0
    ],
    [
      1780665840000,
      "MEASURED",
      59,
      3.0
    ],
    [
      1780666020000,
      "MEASURED",
      58,
      3.0
    ],
    [
      1780666200000,
      "MEASURED",
      58,
      3.0
    ],
    [
      1780666380000,
      "MEASURED",
      57,
      3.0
    ],
    [
      1780666560000,
      "MEASURED",
      57,
      3.0
    ],
    [
      1780666740000,
      "MEASURED",
      57,
      3.0
    ],
    [
      1780666920000,
      "MEASURED",
      56,
      3.0
    ],
    [
      1780667100000,
      "MEASURED",
      56,
      3.0
    ],
    [
      1780667280000,
      "MEASURED",
      56,
      3.0
    ],
    [
      1780667460000,
      "MEASURED",
      56,
      3.0
    ],
    [
      1780667640000,
      "MEASURED",
      55,
      3.0
    ],
    [
      1780667820000,
      "MEASURED",
      55,
      3.0
    ],
    [
      1780668000000,
      "MEASURED",
      55,
      3.0
    ],
    [
      1780668180000,
      "MEASURED",
      54,
      3.0
    ],
    [
      1780668360000,
      "MEASURED",
      54,
      3.0
    ],
    [
      1780668540000,
      "MEASURED",
      54,
      3.0
    ],
    [
      1780668720000,
      "MEASURED",
      53,
      3.0
    ],
    [
      1780668900000,
      "MEASURED",
      53,
      3.0
    ],
    [
      1780669080000,
      "MEASURED",
      53,
      3.0
    ],
    [
      1780669260000,
      "MEASURED",
      52,
      3.0
    ],
    [
      1780669440000,
      "MEASURED",
      52,
      3.0
    ],
    [
      1780669620000,
      "MEASURED",
      52,
      3.0
    ],
    [
      1780669800000,
      "MEASURED",
      51,
      3.0
    ],
    [
      1780669980000,
      "MEASURED",
      51,
      3.0
    ],
    [
      1780670160000,
      "MEASURED",
      51,
      3.0
    ],
    [
      1780670340000,
      "MEASURED",
      51,
      3.0
    ],
    [
      1780670520000,
      "MEASURED",
      50,
      3.0
    ],
    [
      1780670700000,
      "MEASURED",
      50,
      3.0
    ],
    [
      1780670880000,
      "MEASURED",
      50,
      3.0
    ],
    [
      1780671060000,
      "MEASURED",
      50,
      3.0
    ],
    [
      1780671240000,
      "MEASURED",
      50,
      3.0
    ],
    [
      1780671420000,
      "MEASURED",
      49,
      3.0
    ],
    [
      1780671600000,
      "MEASURED",
      49,
      3.0
    ],
    [
      1780671780000,
      "MEASURED",
      49,
      3.0
    ],
    [
      1780671960000,
      "MEASURED",
      49,
      3.0
    ],
    [
      1780672140000,
      "MEASURED",
      49,
      3.0
    ],
    [
      1780672320000,
      "MEASURED",
      48,
      3.0
    ],
    [
      1780672500000,
      "MEASURED",
      48,
      3.0
    ],
    [
      1780672680000,
      "MEASURED",
      48,
      3.0
    ],
    [
      1780672860000,
      "MEASURED",
      48,
      3.0
    ],
    [
      1780673040000,
      "MEASURED",
      47,
      3.0
    ],
    [
      1780673220000,
      "MEASURED",
      47,
      3.0
    ],
    [
      1780673400000,
      "MEASURED",
      47,
      3.0
    ],
    [
      1780673580000,
      "MEASURED",
      46,
      3.0
    ],
    [
      1780673760000,
      "MEASURED",
      46,
      3.0
    ],
    [
      1780673940000,
      "MEASURED",
      46,
      3.0
    ],
    [
      1780674120000,
      "MEASURED",
      46,
      3.0
    ],
    [
      1780674300000,
      "MEASURED",
      46,
      3.0
    ],
    [
      1780674480000,
      "MEASURED",
      46,
      3.0
    ],
    [
      1780674660000,
      "MEASURED",
      46,
      3.0
    ],
    [
      1780674840000,
      "MEASURED",
      45,
      3.0
    ],
    [
      1780675020000,
      "MEASURED",
      45,
      3.0
    ],
    [
      1780675200000,
      "MEASURED",
      45,
      3.0
    ],
    [
      1780675380000,
      "MEASURED",
      45,
      3.0
    ],
    [
      1780675560000,
      "MEASURED",
      45,
      3.0
    ],
    [
      1780675740000,
      "MEASURED",
      44,
      3.0
    ],
    [
      1780675920000,
      "MEASURED",
      44,
      3.0
    ],
    [
      1780676100000,
      "MEASURED",
      44,
      3.0
    ],
    [
      1780676280000,
      "MEASURED",
      44,
      3.0
    ],
    [
      1780676460000,
      "MEASURED",
      44,
      3.0
    ],
    [
      1780676640000,
      "MEASURED",
      44,
      3.0
    ],
    [
      1780676820000,
      "MEASURED",
      43,
      3.0
    ],
    [
      1780677000000,
      "MEASURED",
      43,
      3.0
    ],
    [
      1780677180000,
      "MEASURED",
      43,
      3.0
    ],
    [
      1780677360000,
      "MEASURED",
      43,
      3.0
    ],
    [
      1780677540000,
      "MEASURED",
      42,
      3.0
    ],
    [
      1780677720000,
      "MEASURED",
      42,
      3.0
    ],
    [
      1780677900000,
      "MEASURED",
      42,
      3.0
    ],
    [
      1780678080000,
      "MEASURED",
      42,
      3.0
    ],
    [
      1780678260000,
      "MEASURED",
      42,
      3.0
    ],
    [
      1780678440000,
      "MEASURED",
      41,
      3.0
    ],
    [
      1780678620000,
      "MEASURED",
      41,
      3.0
    ],
    [
      1780678800000,
      "MEASURED",
      41,
      3.0
    ],
    [
      1780678980000,
      "MEASURED",
      41,
      3.0
    ],
    [
      1780679160000,
      "MEASURED",
      41,
      3.0
    ],
    [
      1780679340000,
      "MEASURED",
      40,
      3.0
    ],
    [
      1780679520000,
      "MEASURED",
      40,
      3.0
    ],
    [
      1780679700000,
      "MEASURED",
      40,
      3.0
    ],
    [
      1780679880000,
      "MEASURED",
      39,
      3.0
    ],
    [
      1780680060000,
      "MEASURED",
      39,
      3.0
    ],
    [
      1780690860000,
      "RESET",
      28,
      3.0
    ],
    [
      1780691040000,
      "MEASURED",
      28,
      3.0
    ],
    [
      1780691220000,
      "MEASURED",
      28,
      3.0
    ],
    [
      1780691400000,
      "MEASURED",
      28,
      3.0
    ],
    [
      1780691580000,
      "MEASURED",
      28,
      3.0
    ],
    [
      1780691760000,
      "MEASURED",
      28,
      3.0
    ],
    [
      1780691940000,
      "MEASURED",
      27,
      3.0
    ],
    [
      1780692120000,
      "MEASURED",
      27,
      3.0
    ],
    [
      1780692300000,
      "MEASURED",
      27,
      3.0
    ],
    [
      1780692480000,
      "MEASURED",
      27,
      3.0
    ],
    [
      1780692660000,
      "MEASURED",
      27,
      3.0
    ],
    [
      1780692840000,
      "MEASURED",
      27,
      3.0
    ],
    [
      1780693020000,
      "MEASURED",
      27,
      3.0
    ],
    [
      1780693200000,
      "MEASURED",
      26,
      3.0
    ],
    [
      1780693380000,
      "MEASURED",
      26,
      3.0
    ],
    [
      1780693560000,
      "MEASURED",
      26,
      3.0
    ],
    [
      1780693740000,
      "MEASURED",
      26,
      3.0
    ],
    [
      1780693920000,
      "MEASURED",
      26,
      3.0
    ],
    [
      1780694100000,
      "MEASURED",
      25,
      3.0
    ],
    [
      1780694280000,
      "MEASURED",
      25,
      3.0
    ],
    [
      1780694460000,
      "MEASURED",
      25,
      3.0
    ],
    [
      1780694640000,
      "MEASURED",
      25,
      3.0
    ],
    [
      1780694820000,
      "MEASURED",
      25,
      3.0
    ],
    [
      1780695000000,
      "MEASURED",
      25,
      3.0
    ],
    [
      1780695180000,
      "MEASURED",
      25,
      3.0
    ],
    [
      1780695360000,
      "MEASURED",
      25,
      3.0
    ],
    [
      1780695540000,
      "MEASURED",
      25,
      3.0
    ],
    [
      1780695720000,
      "MEASURED",
      25,
      3.0
    ],
    [
      1780695900000,
      "MEASURED",
      25,
      3.0
    ],
    [
      1780696080000,
      "MEASURED",
      25,
      3.0
    ],
    [
      1780696260000,
      "MEASURED",
      25,
      3.0
    ],
    [
      1780696440000,
      "MODELED",
      24,
      3.0
    ],
    [
      1780696620000,
      "MEASURED",
      24,
      3.0
    ],
    [
      1780696800000,
      "MEASURED",
      24,
      3.0
    ],
    [
      1780696980000,
      "MEASURED",
      24,
      3.0
    ],
    [
      1780697160000,
      "MEASURED",
      24,
      3.0
    ],
    [
      1780697340000,
      "MEASURED",
      23,
      3.0
    ],
    [
      1780697520000,
      "MEASURED",
      23,
      3.0
    ],
    [
      1780697700000,
      "MEASURED",
      23,
      3.0
    ],
    [
      1780697880000,
      "MEASURED",
      23,
      3.0
    ],
    [
      1780698060000,
      "MEASURED",
      23,
      3.0
    ],
    [
      1780698240000,
      "MEASURED",
      23,
      3.0
    ],
    [
      1780698420000,
      "MEASURED",
      23,
      3.0
    ],
    [
      1780698600000,
      "MEASURED",
      23,
      3.0
    ],
    [
      1780698780000,
      "MEASURED",
      22,
      3.0
    ],
    [
      1780698960000,
      "MEASURED",
      22,
      3.0
    ],
    [
      1780699140000,
      "MEASURED",
      22,
      3.0
    ],
    [
      1780699320000,
      "MEASURED",
      22,
      3.0
    ],
    [
      1780699500000,
      "MEASURED",
      22,
      3.0
    ],
    [
      1780699680000,
      "MEASURED",
      22,
      3.0
    ],
    [
      1780699860000,
      "MEASURED",
      22,
      3.0
    ],
    [
      1780700040000,
      "MEASURED",
      22,
      3.0
    ],
    [
      1780700220000,
      "MEASURED",
      22,
      3.0
    ],
    [
      1780700400000,
      "MEASURED",
      22,
      3.0
    ],
    [
      1780700580000,
      "MEASURED",
      21,
      3.0
    ],
    [
      1780700760000,
      "MEASURED",
      21,
      3.0
    ],
    [
      1780700940000,
      "MEASURED",
      21,
      3.0
    ],
    [
      1780701120000,
      "MEASURED",
      21,
      3.0
    ],
    [
      1780701300000,
      "MEASURED",
      21,
      3.0
    ],
    [
      1780701480000,
      "MEASURED",
      21,
      3.0
    ],
    [
      1780701660000,
      "MEASURED",
      21,
      3.0
    ],
    [
      1780701840000,
      "MEASURED",
      21,
      3.0
    ],
    [
      1780702020000,
      "MEASURED",
      21,
      3.0
    ],
    [
      1780702200000,
      "MEASURED",
      21,
      3.0
    ],
    [
      1780702380000,
      "MEASURED",
      21,
      3.0
    ],
    [
      1780702560000,
      "MEASURED",
      21,
      3.0
    ],
    [
      1780702740000,
      "MEASURED",
      21,
      3.0
    ],
    [
      1780702920000,
      "MEASURED",
      21,
      3.0
    ],
    [
      1780703100000,
      "MEASURED",
      20,
      3.0
    ],
    [
      1780703280000,
      "MEASURED",
      20,
      3.0
    ],
    [
      1780703460000,
      "MEASURED",
      20,
      3.0
    ],
    [
      1780703640000,
      "MEASURED",
      20,
      3.0
    ],
    [
      1780703820000,
      "MEASURED",
      20,
      3.0
    ],
    [
      1780704000000,
      "MEASURED",
      20,
      3.0
    ],
    [
      1780704180000,
      "MEASURED",
      20,
      3.0
    ],
    [
      1780704360000,
      "MEASURED",
      20,
      3.0
    ],
    [
      1780704540000,
      "MEASURED",
      20,
      3.0
    ],
    [
      1780704720000,
      "MEASURED",
      20,
      3.0
    ],
    [
      1780704900000,
      "MEASURED",
      19,
      3.0
    ],
    [
      1780705080000,
      "MEASURED",
      19,
      3.0
    ],
    [
      1780705260000,
      "MEASURED",
      19,
      3.0
    ],
    [
      1780705440000,
      "MEASURED",
      19,
      3.0
    ],
    [
      1780705620000,
      "MEASURED",
      19,
      3.0
    ],
    [
      1780705800000,
      "MEASURED",
      19,
      3.0
    ],
    [
      1780705980000,
      "MEASURED",
      19,
      3.0
    ],
    [
      1780706160000,
      "MEASURED",
      19,
      3.0
    ],
    [
      1780706340000,
      "MEASURED",
      19,
      3.0
    ],
    [
      1780706520000,
      "MEASURED",
      19,
      3.0
    ],
    [
      1780706700000,
      "MEASURED",
      18,
      3.0
    ],
    [
      1780706880000,
      "MEASURED",
      18,
      3.0
    ],
    [
      1780707060000,
      "MEASURED",
      18,
      3.0
    ],
    [
      1780707240000,
      "MEASURED",
      18,
      3.0
    ],
    [
      1780707420000,
      "MEASURED",
      18,
      3.0
    ],
    [
      1780707600000,
      "MEASURED",
      18,
      3.0
    ],
    [
      1780707780000,
      "MEASURED",
      18,
      3.0
    ],
    [
      1780707960000,
      "MEASURED",
      18,
      3.0
    ],
    [
      1780708140000,
      "MEASURED",
      18,
      3.0
    ],
    [
      1780708320000,
      "MEASURED",
      18,
      3.0
    ],
    [
      1780708500000,
      "MEASURED",
      18,
      3.0
    ],
    [
      1780708680000,
      "MEASURED",
      18,
      3.0
    ],
    [
      1780708860000,
      "MEASURED",
      18,
      3.0
    ],
    [
      1780709040000,
      "MEASURED",
      19,
      3.0
    ],
    [
      1780709220000,
      "MEASURED",
      20,
      3.0
    ],
    [
      1780709400000,
      "MEASURED",
      20,
      3.0
    ],
    [
      1780709580000,
      "MEASURED",
      20,
      3.0
    ],
    [
      1780709760000,
      "MEASURED",
      20,
      3.0
    ],
    [
      1780709940000,
      "MEASURED",
      21,
      3.0
    ],
    [
      1780710120000,
      "MEASURED",
      21,
      3.0
    ],
    [
      1780710300000,
      "MEASURED",
      21,
      3.0
    ],
    [
      1780710480000,
      "MEASURED",
      22,
      3.0
    ],
    [
      1780710660000,
      "MEASURED",
      22,
      3.0
    ],
    [
      1780710840000,
      "MEASURED",
      23,
      3.0
    ],
    [
      1780711020000,
      "MEASURED",
      23,
      3.0
    ],
    [
      1780711200000,
      "MEASURED",
      24,
      3.0
    ],
    [
      1780711380000,
      "MEASURED",
      24,
      3.0
    ],
    [
      1780711560000,
      "MEASURED",
      24,
      3.0
    ],
    [
      1780711740000,
      "MEASURED",
      25,
      3.0
    ],
    [
      1780711920000,
      "MEASURED",
      25,
      3.0
    ],
    [
      1780712100000,
      "MEASURED",
      25,
      3.0
    ],
    [
      1780712280000,
      "MEASURED",
      26,
      3.0
    ],
    [
      1780712460000,
      "MEASURED",
      26,
      3.0
    ],
    [
      1780712640000,
      "MEASURED",
      27,
      3.0
    ],
    [
      1780712820000,
      "MEASURED",
      27,
      3.0
    ],
    [
      1780713000000,
      "MEASURED",
      28,
      3.0
    ],
    [
      1780713180000,
      "MEASURED",
      28,
      3.0
    ],
    [
      1780713360000,
      "MEASURED",
      28,
      3.0
    ],
    [
      1780713540000,
      "MEASURED",
      28,
      3.0
    ],
    [
      1780713720000,
      "MEASURED",
      29,
      3.0
    ],
    [
      1780713900000,
      "MEASURED",
      29,
      3.0
    ],
    [
      1780714080000,
      "MEASURED",
      29,
      3.0
    ],
    [
      1780714260000,
      "MEASURED",
      30,
      3.0
    ],
    [
      1780714440000,
      "MEASURED",
      31,
      3.0
    ],
    [
      1780714620000,
      "MEASURED",
      31,
      3.0
    ]
  ]
}