{
  "userProfilePK": 131621693,
  "calendarDate": "2026-05-17",
  "startTimestampGMT": "2026-05-17T03:00:00.0",
  "endTimestampGMT": "2026-05-18T03:00:00.0",
  "startTimestampLocal": "2026-05-17T00:00:00.0",
  "endTimestampLocal": "2026-05-18T00:00:00.0",
  "maxStressLevel": 95,
  "avgStressLevel": 38,
  "stressChartValueOffset": 1,
  "stressChartYAxisOrigin": -1,
  "stressValueDescriptorsDTOList": [
    {
      "index": 0,
      "key": "timestamp"
    },
    {
      "index": 1,
      "key": "stressLevel"
    }
  ],
  "stressValuesArray": [
    [
      1778986800000,
      9
    ],
    [
      1778986980000,
      19
    ],
    [
      1778987160000,
      13
    ],
    [
      1778987340000,
      15
    ],
    [
      1778987520000,
      16
    ],
    [
      1778987700000,
      14
    ],
    [
      1778987880000,
      19
    ],
    [
      1778988060000,
      13
    ],
    [
      1778988240000,
      9
    ],
    [
      1778988420000,
      11
    ],
    [
      1778988600000,
      11
    ],
    [
      1778988780000,
      12
    ],
    [
      1778988960000,
      13
    ],
    [
      1778989140000,
      9
    ],
    [
      1778989320000,
      12
    ],
    [
      1778989500000,
      16
    ],
    [
      1778989680000,
      15
    ],
    [
      1778989860000,
      16
    ],
    [
      1778990040000,
      15
    ],
    [
      1778990220000,
      14
    ],
    [
      1778990400000,
      12
    ],
    [
      1778990580000,
      15
    ],
    [
      1778990760000,
      13
    ],
    [
      1778990940000,
      9
    ],
    [
      1778991120000,
      10
    ],
    [
      1778991300000,
      16
    ],
    [
      1778991480000,
      13
    ],
    [
      1778991660000,
      15
    ],
    [
      1778991840000,
      15
    ],
    [
      1778992020000,
      15
    ],
    [
      1778992200000,
      17
    ],
    [
      1778992380000,
      16
    ],
    [
      1778992560000,
      13
    ],
    [
      1778992740000,
      13
    ],
    [
      1778992920000,
      8
    ],
    [
      1778993100000,
      9
    ],
    [
      1778993280000,
      10
    ],
    [
      1778993460000,
      9
    ],
    [
      1778993640000,
      20
    ],
    [
      1778993820000,
      20
    ],
    [
      1778994000000,
      19
    ],
    [
      1778994180000,
      17
    ],
    [
      1778994360000,
      17
    ],
    [
      1778994540000,
      14
    ],
    [
      1778994720000,
      15
    ],
    [
      1778994900000,
      12
    ],
    [
      1778995080000,
      8
    ],
    [
      1778995260000,
      8
    ],
    [
      1778995440000,
      10
    ],
    [
      1778995620000,
      7
    ],
    [
      1778995800000,
      7
    ],
    [
      1778995980000,
      8
    ],
    [
      1778996160000,
      7
    ],
    [
      1778996340000,
      8
    ],
    [
      1778996520000,
      8
    ],
    [
      1778996700000,
      16
    ],
    [
      1778996880000,
      11
    ],
    [
      1778997060000,
      15
    ],
    [
      1778997240000,
      11
    ],
    [
      1778997420000,
      5
    ],
    [
      1778997600000,
      7
    ],
    [
      1778997780000,
      13
    ],
    [
      1778997960000,
      17
    ],
    [
      1778998140000,
      14
    ],
    [
      1778998320000,
      14
    ],
    [
      1778998500000,
      16
    ],
    [
      1778998680000,
      13
    ],
    [
      1778998860000,
      12
    ],
    [
      1778999040000,
      20
    ],
    [
      1778999220000,
      19
    ],
    [
      1778999400000,
      24
    ],
    [
      1778999580000,
      18
    ],
    [
      1778999760000,
      22
    ],
    [
      1778999940000,
      16
    ],
    [
      1779000120000,
      19
    ],
    [
      1779000300000,
      15
    ],
    [
      1779000480000,
      15
    ],
    [
      1779000660000,
      19
    ],
    [
      1779000840000,
      20
    ],
    [
      1779001020000,
      17
    ],
    [
      1779001200000,
      17
    ],
    [
      1779001380000,
      16
    ],
    [
      1779001560000,
      13
    ],
    [
      1779001740000,
      12
    ],
    [
      1779001920000,
      10
    ],
    [
      1779002100000,
      7
    ],
    [
      1779002280000,
      8
    ],
    [
      1779002460000,
      -1
    ],
    [
      1779002640000,
      -1
    ],
    [
      1779002820000,
      -1
    ],
    [
      1779003000000,
      -2
    ],
    [
      1779003180000,
      23
    ],
    [
      1779003360000,
      17
    ],
    [
      1779003540000,
      -1
    ],
    [
      1779003720000,
      -1
    ],
    [
      1779003900000,
      -1
    ],
    [
      1779004080000,
      59
    ],
    [
      1779004260000,
      35
    ],
    [
      1779004440000,
      -1
    ],
    [
      1779004620000,
      24
    ],
    [
      1779004800000,
      21
    ],
    [
      1779004980000,
      -1
    ],
    [
      1779005160000,
      -2
    ],
    [
      1779005340000,
      -1
    ],
    [
      1779005520000,
      -2
    ],
    [
      1779005700000,
      -1
    ],
    [
      1779005880000,
      -1
    ],
    [
      1779006060000,
      -2
    ],
    [
      1779006240000,
      -2
    ],
    [
      1779006420000,
      -2
    ],
    [
      1779006600000,
      -1
    ],
    [
      1779006780000,
      -1
    ],
    [
      1779006960000,
      28
    ],
    [
      1779007140000,
      46
    ],
    [
      1779007320000,
      46
    ],
    [
      1779007500000,
      -2
    ],
    [
      1779007680000,
      -2
    ],
    [
      1779007860000,
      -1
    ],
    [
      1779008040000,
      -2
    ],
    [
      1779008220000,
      -2
    ],
    [
      1779008400000,
      -2
    ],
    [
      1779008580000,
      -2
    ],
    [
      1779008760000,
      -2
    ],
    [
      1779008940000,
      -2
    ],
    [
      1779009120000,
      -2
    ],
    [
      1779009300000,
      -2
    ],
    [
      1779009480000,
      -2
    ],
    [
      1779009660000,
      -2
    ],
    [
      1779009840000,
      -2
    ],
    [
      1779010020000,
      -2
    ],
    [
      1779010200000,
      -2
    ],
    [
      1779010380000,
      -1
    ],
    [
      1779010560000,
      -1
    ],
    [
      1779010740000,
      -1
    ],
    [
      1779010920000,
      -1
    ],
    [
      1779011100000,
      -1
    ],
    [
      1779011280000,
      -1
    ],
    [
      1779011460000,
      -1
    ],
    [
      1779011640000,
      -1
    ],
    [
      1779011820000,
      -2
    ],
    [
      1779012000000,
      -1
    ],
    [
      1779012180000,
      -2
    ],
    [
      1779012360000,
      -2
    ],
    [
      1779012540000,
      -2
    ],
    [
      1779012720000,
      -1
    ],
    [
      1779012900000,
      -1
    ],
    [
      1779013080000,
      -2
    ],
    [
      1779013260000,
      -2
    ],
    [
      1779013440000,
      -2
    ],
    [
      1779013620000,
      -2
    ],
    [
      1779013800000,
      -2
    ],
    [
      1779013980000,
      -2
    ],
    [
      1779014160000,
      -2
    ],
    [
      1779014340000,
      -2
    ],
    [
      1779014520000,
      -2
    ],
    [
      1779014700000,
      -2
    ],
    [
      1779014880000,
      -2
    ],
    [
      1779015060000,
      -2
    ],
    [
      1779015240000,
      -2
    ],
    [
      1779015420000,
      -2
    ],
    [
      1779015600000,
      -2
    ],
    [
      1779015780000,
      -2
    ],
    [
      1779015960000,
      -1
    ],
    [
      1779016140000,
      -2
    ],
    [
      1779016320000,
      -2
    ],
    [
      1779016500000,
      -2
    ],
    [
      1779016680000,
      -2
    ],
    [
      1779016860000,
      -2
    ],
    [
      1779017040000,
      -1
    ],
    [
      1779017220000,
      -2
    ],
    [
      1779017400000,
      -2
    ],
    [
      1779017580000,
      -2
    ],
    [
      1779017760000,
      -2
    ],
    [
      1779017940000,
      -2
    ],
    [
      1779018120000,
      -1
    ],
    [
      1779018300000,
      -1
    ],
    [
      1779018480000,
      -1
    ],
    [
      1779018660000,
      -2
    ],
    [
      1779018840000,
      -2
    ],
    [
      1779019020000,
      -2
    ],
    [
      1779019200000,
      -2
    ],
    [
      1779019380000,
      -2
    ],
    [
      1779019560000,
      -2
    ],
    [
      1779019740000,
      -2
    ],
    [
      1779019920000,
      -2
    ],
    [
      1779020100000,
      -1
    ],
    [
      1779020280000,
      -1
    ],
    [
      1779020460000,
      -1
    ],
    [
      1779020640000,
      -1
    ],
    [
      1779020820000,
      -2
    ],
    [
      1779021000000,
      -1
    ],
    [
      1779021180000,
      -1
    ],
    [
      1779021360000,
      -1
    ],
    [
      1779021540000,
      -1
    ],
    [
      1779021720000,
      -1
    ],
    [
      1779021900000,
      -2
    ],
    [
      1779022080000,
      -2
    ],
    [
      1779022260000,
      -2
    ],
    [
      1779022440000,
      -2
    ],
    [
      1779022620000,
      -2
    ],
    [
      1779022800000,
      -2
    ],
    [
      1779022980000,
      -1
    ],
    [
      1779023160000,
      -1
    ],
    [
      1779023340000,
      -1
    ],
    [
      1779023520000,
      -1
    ],
    [
      1779023700000,
      -1
    ],
    [
      1779023880000,
      -1
    ],
    [
      1779024060000,
      -1
    ],
    [
      1779024240000,
      70
    ],
    [
      1779024420000,
      81
    ],
    [
      1779024600000,
      -1
    ],
    [
      1779024780000,
      -1
    ],
    [
      1779024960000,
      -1
    ],
    [
      1779025140000,
      -1
    ],
    [
      1779025320000,
      84
    ],
    [
      1779025500000,
      -1
    ],
    [
      1779025680000,
      76
    ],
    [
      1779025860000,
      73
    ],
    [
      1779026040000,
      76
    ],
    [
      1779026220000,
      68
    ],
    [
      1779026400000,
      72
    ],
    [
      1779026580000,
      80
    ],
    [
      1779026760000,
      77
    ],
    [
      1779026940000,
      76
    ],
    [
      1779027120000,
      -2
    ],
    [
      1779027300000,
      78
    ],
    [
      1779027480000,
      73
    ],
    [
      1779027660000,
      -1
    ],
    [
      1779027840000,
      -1
    ],
    [
      1779028020000,
      -1
    ],
    [
      1779028200000,
      85
    ],
    [
      1779028380000,
      82
    ],
    [
      1779028560000,
      82
    ],
    [
      1779028740000,
      84
    ],
    [
      1779028920000,
      84
    ],
    [
      1779029100000,
      92
    ],
    [
      1779029280000,
      77
    ],
    [
      1779029460000,
      -1
    ],
    [
      1779029640000,
      68
    ],
    [
      1779029820000,
      75
    ],
    [
      1779030000000,
      73
    ],
    [
      1779030180000,
      79
    ],
    [
      1779030360000,
      87
    ],
    [
      1779030540000,
      93
    ],
    [
      1779030720000,
      91
    ],
    [
      1779030900000,
      -1
    ],
    [
      1779031080000,
      -1
    ],
    [
      1779031260000,
      82
    ],
    [
      1779031440000,
      76
    ],
    [
      1779031620000,
      73
    ],
    [
      1779031800000,
      -2
    ],
    [
      1779031980000,
      -2
    ],
    [
      1779032160000,
      -1
    ],
    [
      1779032340000,
      -1
    ],
    [
      1779032520000,
      -1
    ],
    [
      1779032700000,
      -1
    ],
    [
      1779032880000,
      -2
    ],
    [
      1779033060000,
      -1
    ],
    [
      1779033240000,
      -1
    ],
    [
      1779033420000,
      -2
    ],
    [
      1779033600000,
      -2
    ],
    [
      1779033780000,
      -1
    ],
    [
      1779033960000,
      -1
    ],
    [
      1779034140000,
      88
    ],
    [
      1779034320000,
      -1
    ],
    [
      1779034500000,
      91
    ],
    [
      1779034680000,
      -1
    ],
    [
      1779034860000,
      -1
    ],
    [
      1779035040000,
      -1
    ],
    [
      1779035220000,
      84
    ],
    [
      1779035400000,
      83
    ],
    [
      1779035580000,
      -1
    ],
    [
      1779035760000,
      81
    ],
    [
      1779035940000,
      70
    ],
    [
      1779036120000,
      -1
    ],
    [
      1779036300000,
      75
    ],
    [
      1779036480000,
      83
    ],
    [
      1779036660000,
      88
    ],
    [
      1779036840000,
      -1
    ],
    [
      1779037020000,
      81
    ],
    [
      1779037200000,
      67
    ],
    [
      1779037380000,
      70
    ],
    [
      1779037560000,
      66
    ],
    [
      1779037740000,
      -2
    ],
    [
      1779037920000,
      -1
    ],
    [
      1779038100000,
      -1
    ],
    [
      1779038280000,
      -1
    ],
    [
      1779038460000,
      -1
    ],
    [
      1779038640000,
      -1
    ],
    [
      1779038820000,
      -1
    ],
    [
      1779039000000,
      -2
    ],
    [
      1779039180000,
      -1
    ],
    [
      1779039360000,
      -1
    ],
    [
      1779039540000,
      79
    ],
    [
      1779039720000,
      79
    ],
    [
      1779039900000,
      -1
    ],
    [
      1779040080000,
      82
    ],
    [
      1779040260000,
      79
    ],
    [
      1779040440000,
      -1
    ],
    [
      1779040620000,
      -2
    ],
    [
      1779040800000,
      -2
    ],
    [
      1779040980000,
      -1
    ],
    [
      1779041160000,
      -1
    ],
    [
      1779041340000,
      -1
    ],
    [
      1779041520000,
      77
    ],
    [
      1779041700000,
      74
    ],
    [
      1779041880000,
      -1
    ],
    [
      1779042060000,
      -1
    ],
    [
      1779042240000,
      -1
    ],
    [
      1779042420000,
      -1
    ],
    [
      1779042600000,
      -1
    ],
    [
      1779042780000,
      -1
    ],
    [
      1779042960000,
      -1
    ],
    [
      1779043140000,
      -1
    ],
    [
      1779043320000,
      -1
    ],
    [
      1779043500000,
      -1
    ],
    [
      1779043680000,
      55
    ],
    [
      1779043860000,
      64
    ],
    [
      1779044040000,
      61
    ],
    [
      1779044220000,
      44
    ],
    [
      1779044400000,
      42
    ],
    [
      1779044580000,
      -1
    ],
    [
      1779044760000,
      67
    ],
    [
      1779044940000,
      -1
    ],
    [
      1779045120000,
      -1
    ],
    [
      1779045300000,
      83
    ],
    [
      1779045480000,
      -2
    ],
    [
      1779045660000,
      -1
    ],
    [
      1779045840000,
      -1
    ],
    [
      1779046020000,
      46
    ],
    [
      1779046200000,
      49
    ],
    [
      1779046380000,
      -1
    ],
    [
      1779046560000,
      -1
    ],
    [
      1779046740000,
      49
    ],
    [
      1779046920000,
      52
    ],
    [
      1779047100000,
      44
    ],
    [
      1779047280000,
      54
    ],
    [
      1779047460000,
      63
    ],
    [
      1779047640000,
      43
    ],
    [
      1779047820000,
      -1
    ],
    [
      1779048000000,
      48
    ],
    [
      1779048180000,
      45
    ],
    [
      1779048360000,
      28
    ],
    [
      1779048540000,
      60
    ],
    [
      1779048720000,
      -1
    ],
    [
      1779048900000,
      -1
    ],
    [
      1779049080000,
      61
    ],
    [
      1779049260000,
      46
    ],
    [
      1779049440000,
      76
    ],
    [
      1779049620000,
      53
    ],
    [
      1779049800000,
      -2
    ],
    [
      1779049980000,
      -1
    ],
    [
      1779050160000,
      56
    ],
    [
      1779050340000,
      49
    ],
    [
      1779050520000,
      44
    ],
    [
      1779050700000,
      44
    ],
    [
      1779050880000,
      40
    ],
    [
      1779051060000,
      43
    ],
    [
      1779051240000,
      34
    ],
    [
      1779051420000,
      53
    ],
    [
      1779051600000,
      40
    ],
    [
      1779051780000,
      57
    ],
    [
      1779051960000,
      55
    ],
    [
      1779052140000,
      52
    ],
    [
      1779052320000,
      44
    ],
    [
      1779052500000,
      23
    ],
    [
      1779052680000,
      -1
    ],
    [
      1779052860000,
      -1
    ],
    [
      1779053040000,
      -1
    ],
    [
      1779053220000,
      12
    ],
    [
      1779053400000,
      44
    ],
    [
      1779053580000,
      47
    ],
    [
      1779053760000,
      38
    ],
    [
      1779053940000,
      -1
    ],
    [
      1779054120000,
      -2
    ],
    [
      1779054300000,
      -1
    ],
    [
      1779054480000,
      -2
    ],
    [
      1779054660000,
      -1
    ],
    [
      1779054840000,
      -1
    ],
    [
      1779055020000,
      -2
    ],
    [
      1779055200000,
      -2
    ],
    [
      1779055380000,
      -1
    ],
    [
      1779055560000,
      -1
    ],
    [
      1779055740000,
      -1
    ],
    [
      1779055920000,
      -1
    ],
    [
      1779056100000,
      14
    ],
    [
      1779056280000,
      25
    ],
    [
      1779056460000,
      31
    ],
    [
      1779056640000,
      34
    ],
    [
      1779056820000,
      25
    ],
    [
      1779057000000,
      23
    ],
    [
      1779057180000,
      -1
    ],
    [
      1779057360000,
      -1
    ],
    [
      1779057540000,
      48
    ],
    [
      1779057720000,
      21
    ],
    [
      1779057900000,
      25
    ],
    [
      1779058080000,
      32
    ],
    [
      1779058260000,
      -2
    ],
    [
      1779058440000,
      -1
    ],
    [
      1779058620000,
      -2
    ],
    [
      1779058800000,
      -1
    ],
    [
      1779058980000,
      25
    ],
    [
      1779059160000,
      21
    ],
    [
      1779059340000,
      37
    ],
    [
      1779059520000,
      26
    ],
    [
      1779059700000,
      -1
    ],
    [
      1779059880000,
      -1
    ],
    [
      1779060060000,
      28
    ],
    [
      1779060240000,
      25
    ],
    [
      1779060420000,
      25
    ],
    [
      1779060600000,
      23
    ],
    [
      1779060780000,
      26
    ],
    [
      1779060960000,
      37
    ],
    [
      1779061140000,
      32
    ],
    [
      1779061320000,
      31
    ],
    [
      1779061500000,
      -1
    ],
    [
      1779061680000,
      25
    ],
    [
      1779061860000,
      34
    ],
    [
      1779062040000,
      35
    ],
    [
      1779062220000,
      29
    ],
    [
      1779062400000,
      -1
    ],
    [
      1779062580000,
      24
    ],
    [
      1779062760000,
      39
    ],
    [
      1779062940000,
      -1
    ],
    [
      1779063120000,
      -1
    ],
    [
      1779063300000,
      40
    ],
    [
      1779063480000,
      25
    ],
    [
      1779063660000,
      31
    ],
    [
      1779063840000,
      35
    ],
    [
      1779064020000,
      30
    ],
    [
      1779064200000,
      25
    ],
    [
      1779064380000,
      25
    ],
    [
      1779064560000,
      30
    ],
    [
      1779064740000,
      26
    ],
    [
      1779064920000,
      -2
    ],
    [
      1779065100000,
      -1
    ],
    [
      1779065280000,
      33
    ],
    [
      1779065460000,
      34
    ],
    [
      1779065640000,
      37
    ],
    [
      1779065820000,
      38
    ],
    [
      1779066000000,
      22
    ],
    [
      1779066180000,
      25
    ],
    [
      1779066360000,
      22
    ],
    [
      1779066540000,
      28
    ],
    [
      1779066720000,
      23
    ],
    [
      1779066900000,
      23
    ],
    [
      1779067080000,
      28
    ],
    [
      1779067260000,
      27
    ],
    [
      1779067440000,
      29
    ],
    [
      1779067620000,
      30
    ],
    [
      1779067800000,
      30
    ],
    [
      1779067980000,
      31
    ],
    [
      1779068160000,
      31
    ],
    [
      1779068340000,
      32
    ],
    [
      1779068520000,
      33
    ],
    [
      1779068700000,
      33
    ],
    [
      1779068880000,
      34
    ],
    [
      1779069060000,
      35
    ],
    [
      1779069240000,
      32
    ],
    [
      1779069420000,
      35
    ],
    [
      1779069600000,
      27
    ],
    [
      1779069780000,
      23
    ],
    [
      1779069960000,
      25
    ],
    [
      1779070140000,
      32
    ],
    [
      1779070320000,
      42
    ],
    [
      1779070500000,
      50
    ],
    [
      1779070680000,
      54
    ],
    [
      1779070860000,
      55
    ],
    [
      1779071040000,
      55
    ],
    [
      1779071220000,
      45
    ],
    [
      1779071400000,
      45
    ],
    [
      1779071580000,
      29
    ],
    [
      1779071760000,
      31
    ],
    [
      1779071940000,
      31
    ],
    [
      1779072120000,
      31
    ],
    [
      1779072300000,
      31
    ],
    [
      1779072480000,
      31
    ],
    [
      1779072660000,
      31
    ],
    [
      1779072840000,
      26
    ],
    [
      1779073020000,
      30
    ]
  ],
  "bodyBatteryValueDescriptorsDTOList": [
    {
      "bodyBatteryValueDescriptorIndex": 0,
      "bodyBatteryValueDescriptorKey": "timestamp"
    },
    {
      "bodyBatteryValueDescriptorIndex": 1,
      "bodyBatteryValueDescriptorKey": "bodyBatteryStatus"
    },
    {
      "bodyBatteryValueDescriptorIndex": 2,
      "bodyBatteryValueDescriptorKey": "bodyBatteryLevel"
    },
    {
      "bodyBatteryValueDescriptorIndex": 3,
      "bodyBatteryValueDescriptorKey": "bodyBatteryVersion"
    }
  ],
  "bodyBatteryValuesArray": [
    [
      1778986800000,
      "MEASURED",
      32,
      3.0
    ],
    [
      1778986980000,
      "MEASURED",
      33,
      3.0
    ],
    [
      1778987160000,
      "MEASURED",
      33,
      3.0
    ],
    [
      1778987340000,
      "MEASURED",
      34,
      3.0
    ],
    [
      1778987520000,
      "MEASURED",
      34,
      3.0
    ],
    [
      1778987700000,
      "MEASURED",
      35,
      3.0
    ],
    [
      1778987880000,
      "MEASURED",
      36,
      3.0
    ],
    [
      1778988060000,
      "MEASURED",
      36,
      3.0
    ],
    [
      1778988240000,
      "MEASURED",
      36,
      3.0
    ],
    [
      1778988420000,
      "MEASURED",
      38,
      3.0
    ],
    [
      1778988600000,
      "MEASURED",
      38,
      3.0
    ],
    [
      1778988780000,
      "MEASURED",
      39,
      3.0
    ],
    [
      1778988960000,
      "MEASURED",
      40,
      3.0
    ],
    [
      1778989140000,
      "MEASURED",
      40,
      3.0
    ],
    [
      1778989320000,
      "MEASURED",
      41,
      3.0
    ],
    [
      1778989500000,
      "MEASURED",
      42,
      3.0
    ],
    [
      1778989680000,
      "MEASURED",
      42,
      3.0
    ],
    [
      1778989860000,
      "MEASURED",
      43,
      3.0
    ],
    [
      1778990040000,
      "MEASURED",
      44,
      3.0
    ],
    [
      1778990220000,
      "MEASURED",
      45,
      3.0
    ],
    [
      1778990400000,
      "MEASURED",
      45,
      3.0
    ],
    [
      1778990580000,
      "MEASURED",
      46,
      3.0
    ],
    [
      1778990760000,
      "MEASURED",
      46,
      3.0
    ],
    [
      1778990940000,
      "MEASURED",
      47,
      3.0
    ],
    [
      1778991120000,
      "MEASURED",
      48,
      3.0
    ],
    [
      1778991300000,
      "MEASURED",
      48,
      3.0
    ],
    [
      1778991480000,
      "MEASURED",
      50,
      3.0
    ],
    [
      1778991660000,
      "MEASURED",
      50,
      3.0
    ],
    [
      1778991840000,
      "MEASURED",
      51,
      3.0
    ],
    [
      1778992020000,
      "MEASURED",
      52,
      3.0
    ],
    [
      1778992200000,
      "MEASURED",
      53,
      3.0
    ],
    [
      1778992380000,
      "MEASURED",
      53,
      3.0
    ],
    [
      1778992560000,
      "MEASURED",
      53,
      3.0
    ],
    [
      1778992740000,
      "MEASURED",
      54,
      3.0
    ],
    [
      1778992920000,
      "MEASURED",
      54,
      3.0
    ],
    [
      1778993100000,
      "MEASURED",
      55,
      3.0
    ],
    [
      1778993280000,
      "MEASURED",
      55,
      3.0
    ],
    [
      1778993460000,
      "MEASURED",
      56,
      3.0
    ],
    [
      1778993640000,
      "MEASURED",
      57,
      3.0
    ],
    [
      1778993820000,
      "MEASURED",
      57,
      3.0
    ],
    [
      1778994000000,
      "MEASURED",
      57,
      3.0
    ],
    [
      1778994180000,
      "MEASURED",
      58,
      3.0
    ],
    [
      1778994360000,
      "MEASURED",
      58,
      3.0
    ],
    [
      1778994540000,
      "MEASURED",
      58,
      3.0
    ],
    [
      1778994720000,
      "MEASURED",
      59,
      3.0
    ],
    [
      1778994900000,
      "MEASURED",
      59,
      3.0
    ],
    [
      1778995080000,
      "MEASURED",
      60,
      3.0
    ],
    [
      1778995260000,
      "MEASURED",
      61,
      3.0
    ],
    [
      1778995440000,
      "MEASURED",
      61,
      3.0
    ],
    [
      1778995620000,
      "MEASURED",
      62,
      3.0
    ],
    [
      1778995800000,
      "MEASURED",
      63,
      3.0
    ],
    [
      1778995980000,
      "MEASURED",
      63,
      3.0
    ],
    [
      1778996160000,
      "MEASURED",
      64,
      3.0
    ],
    [
      1778996340000,
      "MEASURED",
      64,
      3.0
    ],
    [
      1778996520000,
      "MEASURED",
      65,
      3.0
    ],
    [
      1778996700000,
      "MEASURED",
      66,
      3.0
    ],
    [
      1778996880000,
      "MEASURED",
      66,
      3.0
    ],
    [
      1778997060000,
      "MEASURED",
      67,
      3.0
    ],
    [
      1778997240000,
      "MEASURED",
      67,
      3.0
    ],
    [
      1778997420000,
      "MEASURED",
      68,
      3.0
    ],
    [
      1778997600000,
      "MEASURED",
      68,
      3.0
    ],
    [
      1778997780000,
      "MEASURED",
      69,
      3.0
    ],
    [
      1778997960000,
      "MEASURED",
      69,
      3.0
    ],
    [
      1778998140000,
      "MEASURED",
      69,
      3.0
    ],
    [
      1778998320000,
      "MEASURED",
      70,
      3.0
    ],
    [
      1778998500000,
      "MEASURED",
      70,
      3.0
    ],
    [
      1778998680000,
      "MEASURED",
      71,
      3.0
    ],
    [
      1778998860000,
      "MEASURED",
      71,
      3.0
    ],
    [
      1778999040000,
      "MEASURED",
      72,
      3.0
    ],
    [
      1778999220000,
      "MEASURED",
      73,
      3.0
    ],
    [
      1778999400000,
      "MEASURED",
      73,
      3.0
    ],
    [
      1778999580000,
      "MEASURED",
      73,
      3.0
    ],
    [
      1778999760000,
      "MEASURED",
      73,
      3.0
    ],
    [
      1778999940000,
      "MEASURED",
      74,
      3.0
    ],
    [
      1779000120000,
      "MEASURED",
      74,
      3.0
    ],
    [
      1779000300000,
      "MEASURED",
      74,
      3.0
    ],
    [
      1779000480000,
      "MEASURED",
      74,
      3.0
    ],
    [
      1779000660000,
      "MEASURED",
      75,
      3.0
    ],
    [
      1779000840000,
      "MEASURED",
      75,
      3.0
    ],
    [
      1779001020000,
      "MEASURED",
      75,
      3.0
    ],
    [
      1779001200000,
      "MEASURED",
      75,
      3.0
    ],
    [
      1779001380000,
      "MEASURED",
      76,
      3.0
    ],
    [
      1779001560000,
      "MEASURED",
      76,
      3.0
    ],
    [
      1779001740000,
      "MEASURED",
      77,
      3.0
    ],
    [
      1779001920000,
      "MEASURED",
      77,
      3.0
    ],
    [
      1779002100000,
      "MEASURED",
      78,
      3.0
    ],
    [
      1779002280000,
      "MEASURED",
      78,
      3.0
    ],
    [
      1779002460000,
      "MEASURED",
      78,
      3.0
    ],
    [
      1779002640000,
      "MEASURED",
      78,
      3.0
    ],
    [
      1779002820000,
      "MEASURED",
      78,
      3.0
    ],
    [
      1779003000000,
      "MEASURED",
      78,
      3.0
    ],
    [
      1779003180000,
      "MEASURED",
      78,
      3.0
    ],
    [
      1779003360000,
      "MEASURED",
      78,
      3.0
    ],
    [
      1779003540000,
      "MEASURED",
      78,
      3.0
    ],
    [
      1779003720000,
      "MEASURED",
      78,
      3.0
    ],
    [
      1779003900000,
      "MEASURED",
      77,
      3.0
    ],
    [
      1779004080000,
      "MEASURED",
      77,
      3.0
    ],
    [
      1779004260000,
      "MEASURED",
      76,
      3.0
    ],
    [
      1779004440000,
      "MEASURED",
      76,
      3.0
    ],
    [
      1779004620000,
      "MEASURED",
      76,
      3.0
    ],
    [
      1779004800000,
      "MEASURED",
      75,
      3.0
    ],
    [
      1779004980000,
      "MEASURED",
      75,
      3.0
    ],
    [
      1779005160000,
      "MEASURED",
      75,
      3.0
    ],
    [
      1779005340000,
      "MEASURED",
      75,
      3.0
    ],
    [
      1779005520000,
      "MEASURED",
      75,
      3.0
    ],
    [
      1779005700000,
      "MEASURED",
      75,
      3.0
    ],
    [
      1779005880000,
      "MEASURED",
      75,
      3.0
    ],
    [
      1779006060000,
      "MEASURED",
      74,
      3.0
    ],
    [
      1779006240000,
      "MEASURED",
      74,
      3.0
    ],
    [
      1779006420000,
      "MEASURED",
      74,
      3.0
    ],
    [
      1779006600000,
      "MEASURED",
      73,
      3.0
    ],
    [
      1779006780000,
      "MEASURED",
      73,
      3.0
    ],
    [
      1779006960000,
      "MEASURED",
      73,
      3.0
    ],
    [
      1779007140000,
      "MEASURED",
      72,
      3.0
    ],
    [
      1779007320000,
      "MEASURED",
      72,
      3.0
    ],
    [
      1779007500000,
      "MEASURED",
      72,
      3.0
    ],
    [
      1779007680000,
      "MEASURED",
      71,
      3.0
    ],
    [
      1779007860000,
      "MEASURED",
      71,
      3.0
    ],
    [
      1779008040000,
      "MEASURED",
      71,
      3.0
    ],
    [
      1779008220000,
      "MEASURED",
      70,
      3.0
    ],
    [
      1779008400000,
      "MEASURED",
      70,
      3.0
    ],
    [
      1779008580000,
      "MEASURED",
      70,
      3.0
    ],
    [
      1779008760000,
      "MEASURED",
      69,
      3.0
    ],
    [
      1779008940000,
      "MEASURED",
      68,
      3.0
    ],
    [
      1779009120000,
      "MEASURED",
      67,
      3.0
    ],
    [
      1779009300000,
      "MEASURED",
      66,
      3.0
    ],
    [
      1779009480000,
      "MEASURED",
      65,
      3.0
    ],
    [
      1779009660000,
      "MEASURED",
      64,
      3.0
    ],
    [
      1779009840000,
      "MEASURED",
      64,
      3.0
    ],
    [
      1779010020000,
      "MEASURED",
      63,
      3.0
    ],
    [
      1779010200000,
      "MEASURED",
      62,
      3.0
    ],
    [
      1779010380000,
      "MEASURED",
      62,
      3.0
    ],
    [
      1779010560000,
      "MEASURED",
      62,
      3.0
    ],
    [
      1779010740000,
      "MEASURED",
      61,
      3.0
    ],
    [
      1779010920000,
      "MEASURED",
      61,
      3.0
    ],
    [
      1779011100000,
      "MEASURED",
      61,
      3.0
    ],
    [
      1779011280000,
      "MEASURED",
      61,
      3.0
    ],
    [
      1779011460000,
      "MEASURED",
      60,
      3.0
    ],
    [
      1779011640000,
      "MEASURED",
      60,
      3.0
    ],
    [
      1779011820000,
      "MEASURED",
      60,
      3.0
    ],
    [
      1779012000000,
      "MEASURED",
      60,
      3.0
    ],
    [
      1779012180000,
      "MEASURED",
      59,
      3.0
    ],
    [
      1779012360000,
      "MEASURED",
      58,
      3.0
    ],
    [
      1779012540000,
      "MEASURED",
      57,
      3.0
    ],
    [
      1779012720000,
      "MEASURED",
      57,
      3.0
    ],
    [
      1779012900000,
      "MEASURED",
      57,
      3.0
    ],
    [
      1779013080000,
      "MEASURED",
      56,
      3.0
    ],
    [
      1779013260000,
      "MEASURED",
      56,
      3.0
    ],
    [
      1779013440000,
      "MEASURED",
      55,
      3.0
    ],
    [
      1779013620000,
      "MEASURED",
      54,
      3.0
    ],
    [
      1779013800000,
      "MEASURED",
      53,
      3.0
    ],
    [
      1779013980000,
      "MEASURED",
      52,
      3.0
    ],
    [
      1779014160000,
      "MEASURED",
      52,
      3.0
    ],
    [
      1779014340000,
      "MEASURED",
      51,
      3.0
    ],
    [
      1779014520000,
      "MEASURED",
      50,
      3.0
    ],
    [
      1779014700000,
      "MEASURED",
      49,
      3.0
    ],
    [
      1779014880000,
      "MEASURED",
      49,
      3.0
    ],
    [
      1779015060000,
      "MEASURED",
      48,
      3.0
    ],
    [
      1779015240000,
      "MEASURED",
      47,
      3.0
    ],
    [
      1779015420000,
      "MEASURED",
      46,
      3.0
    ],
    [
      1779015600000,
      "MEASURED",
      45,
      3.0
    ],
    [
      1779015780000,
      "MEASURED",
      45,
      3.0
    ],
    [
      1779015960000,
      "MEASURED",
      45,
      3.0
    ],
    [
      1779016140000,
      "MEASURED",
      45,
      3.0
    ],
    [
      1779016320000,
      "MEASURED",
      44,
      3.0
    ],
    [
      1779016500000,
      "MEASURED",
      44,
      3.0
    ],
    [
      1779016680000,
      "MEASURED",
      44,
      3.0
    ],
    [
      1779016860000,
      "MEASURED",
      44,
      3.0
    ],
    [
      1779017040000,
      "MEASURED",
      44,
      3.0
    ],
    [
      1779017220000,
      "MEASURED",
      44,
      3.0
    ],
    [
      1779017400000,
      "MEASURED",
      44,
      3.0
    ],
    [
      1779017580000,
      "MEASURED",
      44,
      3.0
    ],
    [
      1779017760000,
      "MEASURED",
      43,
      3.0
    ],
    [
      1779017940000,
      "MEASURED",
      43,
      3.0
    ],
    [
      1779018120000,
      "MEASURED",
      43,
      3.0
    ],
    [
      1779018300000,
      "MEASURED",
      43,
      3.0
    ],
    [
      1779018480000,
      "MEASURED",
      43,
      3.0
    ],
    [
      1779018660000,
      "MEASURED",
      42,
      3.0
    ],
    [
      1779018840000,
      "MEASURED",
      42,
      3.0
    ],
    [
      1779019020000,
      "MEASURED",
      42,
      3.0
    ],
    [
      1779019200000,
      "MEASURED",
      42,
      3.0
    ],
    [
      1779019380000,
      "MEASURED",
      42,
      3.0
    ],
    [
      1779019560000,
      "MEASURED",
      42,
      3.0
    ],
    [
      1779019740000,
      "MEASURED",
      42,
      3.0
    ],
    [
      1779019920000,
      "MEASURED",
      41,
      3.0
    ],
    [
      1779020100000,
      "MEASURED",
      41,
      3.0
    ],
    [
      1779020280000,
      "MEASURED",
      41,
      3.0
    ],
    [
      1779020460000,
      "MEASURED",
      41,
      3.0
    ],
    [
      1779020640000,
      "MEASURED",
      40,
      3.0
    ],
    [
      1779020820000,
      "MEASURED",
      40,
      3.0
    ],
    [
      1779021000000,
      "MEASURED",
      40,
      3.0
    ],
    [
      1779021180000,
      "MEASURED",
      40,
      3.0
    ],
    [
      1779021360000,
      "MEASURED",
      40,
      3.0
    ],
    [
      1779021540000,
      "MEASURED",
      40,
      3.0
    ],
    [
      1779021720000,
      "MEASURED",
      40,
      3.0
    ],
    [
      1779021900000,
      "MEASURED",
      40,
      3.0
    ],
    [
      1779022080000,
      "MEASURED",
      40,
      3.0
    ],
    [
      1779022260000,
      "MEASURED",
      39,
      3.0
    ],
    [
      1779022440000,
      "MEASURED",
      39,
      3.0
    ],
    [
      1779022620000,
      "MEASURED",
      39,
      3.0
    ],
    [
      1779022800000,
      "MEASURED",
      39,
      3.0
    ],
    [
      1779022980000,
      "MEASURED",
      38,
      3.0
    ],
    [
      1779023160000,
      "MEASURED",
      38,
      3.0
    ],
    [
      1779023340000,
      "MEASURED",
      38,
      3.0
    ],
    [
      1779023520000,
      "MEASURED",
      38,
      3.0
    ],
    [
      1779023700000,
      "MEASURED",
      38,
      3.0
    ],
    [
      1779023880000,
      "MEASURED",
      38,
      3.0
    ],
    [
      1779024060000,
      "MEASURED",
      38,
      3.0
    ],
    [
      1779024240000,
      "MEASURED",
      38,
      3.0
    ],
    [
      1779024420000,
      "MEASURED",
      37,
      3.0
    ],
    [
      1779024600000,
      "MEASURED",
      37,
      3.0
    ],
    [
      1779024780000,
      "MEASURED",
      37,
      3.0
    ],
    [
      1779024960000,
      "MEASURED",
      37,
      3.0
    ],
    [
      1779025140000,
      "MEASURED",
      37,
      3.0
    ],
    [
      1779025320000,
      "MEASURED",
      36,
      3.0
    ],
    [
      1779025500000,
      "MEASURED",
      36,
      3.0
    ],
    [
      1779025680000,
      "MEASURED",
      36,
      3.0
    ],
    [
      1779025860000,
      "MEASURED",
      35,
      3.0
    ],
    [
      1779026040000,
      "MEASURED",
      35,
      3.0
    ],
    [
      1779026220000,
      "MEASURED",
      35,
      3.0
    ],
    [
      1779026400000,
      "MEASURED",
      35,
      3.0
    ],
    [
      1779026580000,
      "MEASURED",
      34,
      3.0
    ],
    [
      1779026760000,
      "MEASURED",
      34,
      3.0
    ],
    [
      1779026940000,
      "MEASURED",
      34,
      3.0
    ],
    [
      1779027120000,
      "MEASURED",
      34,
      3.0
    ],
    [
      1779027300000,
      "MEASURED",
      32,
      3.0
    ],
    [
      1779027480000,
      "MEASURED",
      32,
      3.0
    ],
    [
      1779027660000,
      "MEASURED",
      32,
      3.0
    ],
    [
      1779027840000,
      "MEASURED",
      32,
      3.0
    ],
    [
      1779028020000,
      "MEASURED",
      32,
      3.0
    ],
    [
      1779028200000,
      "MEASURED",
      31,
      3.0
    ],
    [
      1779028380000,
      "MEASURED",
      31,
      3.0
    ],
    [
      1779028560000,
      "MEASURED",
      31,
      3.0
    ],
    [
      1779028740000,
      "MEASURED",
      30,
      3.0
    ],
    [
      1779028920000,
      "MEASURED",
      30,
      3.0
    ],
    [
      1779029100000,
      "MEASURED",
      30,
      3.0
    ],
    [
      1779029280000,
      "MEASURED",
      30,
      3.0
    ],
    [
      1779029460000,
      "MEASURED",
      29,
      3.0
    ],
    [
      1779029640000,
      "MEASURED",
      29,
      3.0
    ],
    [
      1779029820000,
      "MEASURED",
      29,
      3.0
    ],
    [
      1779030000000,
      "MEASURED",
      29,
      3.0
    ],
    [
      1779030180000,
      "MEASURED",
      28,
      3.0
    ],
    [
      1779030360000,
      "MEASURED",
      28,
      3.0
    ],
    [
      1779030540000,
      "MEASURED",
      28,
      3.0
    ],
    [
      1779030720000,
      "MEASURED",
      27,
      3.0
    ],
    [
      1779030900000,
      "MEASURED",
      27,
      3.0
    ],
    [
      1779031080000,
      "MEASURED",
      27,
      3.0
    ],
    [
      1779031260000,
      "MEASURED",
      27,
      3.0
    ],
    [
      1779031440000,
      "MEASURED",
      26,
      3.0
    ],
    [
      1779031620000,
      "MEASURED",
      26,
      3.0
    ],
    [
      1779031800000,
      "MEASURED",
      26,
      3.0
    ],
    [
      1779031980000,
      "MEASURED",
      25,
      3.0
    ],
    [
      1779032160000,
      "MEASURED",
      25,
      3.0
    ],
    [
      1779032340000,
      "MEASURED",
      25,
      3.0
    ],
    [
      1779032520000,
      "MEASURED",
      25,
      3.0
    ],
    [
      1779032700000,
      "MEASURED",
      24,
      3.0
    ],
    [
      1779032880000,
      "MEASURED",
      24,
      3.0
    ],
    [
      1779033060000,
      "MEASURED",
      24,
      3.0
    ],
    [
      1779033240000,
      "MEASURED",
      24,
      3.0
    ],
    [
      1779033420000,
      "MEASURED",
      23,
      3.0
    ],
    [
      1779033600000,
      "MEASURED",
      23,
      3.0
    ],
    [
      1779033780000,
      "MEASURED",
      23,
      3.0
    ],
    [
      1779033960000,
      "MEASURED",
      23,
      3.0
    ],
    [
      1779034140000,
      "MEASURED",
      23,
      3.0
    ],
    [
      1779034320000,
      "MEASURED",
      22,
      3.0
    ],
    [
      1779034500000,
      "MEASURED",
      22,
      3.0
    ],
    [
      1779034680000,
      "MEASURED",
      22,
      3.0
    ],
    [
      1779034860000,
      "MEASURED",
      21,
      3.0
    ],
    [
      1779035040000,
      "MEASURED",
      21,
      3.0
    ],
    [
      1779035220000,
      "MEASURED",
      21,
      3.0
    ],
    [
      1779035400000,
      "MEASURED",
      21,
      3.0
    ],
    [
      1779035580000,
      "MEASURED",
      20,
      3.0
    ],
    [
      1779035760000,
      "MEASURED",
      20,
      3.0
    ],
    [
      1779035940000,
      "MEASURED",
      20,
      3.0
    ],
    [
      1779036120000,
      "MEASURED",
      20,
      3.0
    ],
    [
      1779036300000,
      "MEASURED",
      19,
      3.0
    ],
    [
      1779036480000,
      "MEASURED",
      19,
      3.0
    ],
    [
      1779036660000,
      "MEASURED",
      19,
      3.0
    ],
    [
      1779036840000,
      "MEASURED",
      19,
      3.0
    ],
    [
      1779037020000,
      "MEASURED",
      18,
      3.0
    ],
    [
      1779037200000,
      "MEASURED",
      18,
      3.0
    ],
    [
      1779037380000,
      "MEASURED",
      18,
      3.0
    ],
    [
      1779037560000,
      "MEASURED",
      18,
      3.0
    ],
    [
      1779037740000,
      "MEASURED",
      17,
      3.0
    ],
    [
      1779037920000,
      "MEASURED",
      17,
      3.0
    ],
    [
      1779038100000,
      "MEASURED",
      17,
      3.0
    ],
    [
      1779038280000,
      "MEASURED",
      17,
      3.0
    ],
    [
      1779038460000,
      "MEASURED",
      16,
      3.0
    ],
    [
      1779038640000,
      "MEASURED",
      16,
      3.0
    ],
    [
      1779038820000,
      "MEASURED",
      16,
      3.0
    ],
    [
      1779039000000,
      "MEASURED",
      16,
      3.0
    ],
    [
      1779039180000,
      "MEASURED",
      16,
      3.0
    ],
    [
      1779039360000,
      "MEASURED",
      15,
      3.0
    ],
    [
      1779039540000,
      "MEASURED",
      15,
      3.0
    ],
    [
      1779039720000,
      "MEASURED",
      15,
      3.0
    ],
    [
      1779039900000,
      "MEASURED",
      15,
      3.0
    ],
    [
      1779040080000,
      "MEASURED",
      14,
      3.0
    ],
    [
      1779040260000,
      "MEASURED",
      14,
      3.0
    ],
    [
      1779040440000,
      "MEASURED",
      14,
      3.0
    ],
    [
      1779040620000,
      "MEASURED",
      14,
      3.0
    ],
    [
      1779040800000,
      "MEASURED",
      14,
      3.0
    ],
    [
      1779040980000,
      "MEASURED",
      14,
      3.0
    ],
    [
      1779041160000,
      "MEASURED",
      14,
      3.0
    ],
    [
      1779041340000,
      "MEASURED",
      14,
      3.0
    ],
    [
      1779041520000,
      "MEASURED",
      14,
      3.0
    ],
    [
      1779041700000,
      "MEASURED",
      14,
      3.0
    ],
    [
      1779041880000,
      "MEASURED",
      14,
      3.0
    ],
    [
      1779042060000,
      "MEASURED",
      14,
      3.0
    ],
    [
      1779042240000,
      "MEASURED",
      14,
      3.0
    ],
    [
      1779042420000,
      "MEASURED",
      14,
      3.0
    ],
    [
      1779042600000,
      "RESET",
      14,
      3.0
    ],
    [
      1779042780000,
      "MODELED",
      14,
      3.0
    ],
    [
      1779042960000,
      "MODELED",
      14,
      3.0
    ],
    [
      1779043140000,
      "MODELED",
      14,
      3.0
    ],
    [
      1779043320000,
      "MODELED",
      13,
      3.0
    ],
    [
      1779043500000,
      "MODELED",
      13,
      3.0
    ],
    [
      1779043680000,
      "MEASURED",
      13,
      3.0
    ],
    [
      1779043860000,
      "MEASURED",
      13,
      3.0
    ],
    [
      1779044040000,
      "MEASURED",
      13,
      3.0
    ],
    [
      1779044220000,
      "MEASURED",
      13,
      3.0
    ],
    [
      1779044400000,
      "MEASURED",
      13,
      3.0
    ],
    [
      1779044580000,
      "MEASURED",
      13,
      3.0
    ],
    [
      1779044760000,
      "MEASURED",
      13,
      3.0
    ],
    [
      1779044940000,
      "MEASURED",
      12,
      3.0
    ],
    [
      1779045120000,
      "MEASURED",
      12,
      3.0
    ],
    [
      1779045300000,
      "MEASURED",
      12,
      3.0
    ],
    [
      1779045480000,
      "MEASURED",
      12,
      3.0
    ],
    [
      1779045660000,
      "MEASURED",
      12,
      3.0
    ],
    [
      1779045840000,
      "MEASURED",
      11,
      3.0
    ],
    [
      1779046020000,
      "MEASURED",
      11,
      3.0
    ],
    [
      1779046200000,
      "MEASURED",
      11,
      3.0
    ],
    [
      1779046380000,
      "MEASURED",
      11,
      3.0
    ],
    [
      1779046560000,
      "MEASURED",
      11,
      3.0
    ],
    [
      1779046740000,
      "MEASURED",
      11,
      3.0
    ],
    [
      1779046920000,
      "MEASURED",
      11,
      3.0
    ],
    [
      1779047100000,
      "MEASURED",
      11,
      3.0
    ],
    [
      1779047280000,
      "MEASURED",
      11,
      3.0
    ],
    [
      1779047460000,
      "MEASURED",
      11,
      3.0
    ],
    [
      1779047640000,
      "MEASURED",
      11,
      3.0
    ],
    [
      1779047820000,
      "MEASURED",
      11,
      3.0
    ],
    [
      1779048000000,
      "MEASURED",
      11,
      3.0
    ],
    [
      1779048180000,
      "MEASURED",
      11,
      3.0
    ],
    [
      1779048360000,
      "MEASURED",
      10,
      3.0
    ],
    [
      1779048540000,
      "MEASURED",
      10,
      3.0
    ],
    [
      1779048720000,
      "MEASURED",
      10,
      3.0
    ],
    [
      1779048900000,
      "MEASURED",
      10,
      3.0
    ],
    [
      1779049080000,
      "MEASURED",
      10,
      3.0
    ],
    [
      1779049260000,
      "MEASURED",
      10,
      3.0
    ],
    [
      1779049440000,
      "MEASURED",
      9,
      3.0
    ],
    [
      1779049620000,
      "MEASURED",
      9,
      3.0
    ],
    [
      1779049800000,
      "MEASURED",
      9,
      3.0
    ],
    [
      1779049980000,
      "MEASURED",
      9,
      3.0
    ],
    [
      1779050160000,
      "MEASURED",
      9,
      3.0
    ],
    [
      1779050340000,
      "MEASURED",
      9,
      3.0
    ],
    [
      1779050520000,
      "MEASURED",
      9,
      3.0
    ],
    [
      1779050700000,
      "MEASURED",
      9,
      3.0
    ],
    [
      1779050880000,
      "MEASURED",
      9,
      3.0
    ],
    [
      1779051060000,
      "MEASURED",
      9,
      3.0
    ],
    [
      1779051240000,
      "MEASURED",
      8,
      3.0
    ],
    [
      1779051420000,
      "MEASURED",
      8,
      3.0
    ],
    [
      1779051600000,
      "MEASURED",
      8,
      3.0
    ],
    [
      1779051780000,
      "MEASURED",
      8,
      3.0
    ],
    [
      1779051960000,
      "MEASURED",
      8,
      3.0
    ],
    [
      1779052140000,
      "MEASURED",
      8,
      3.0
    ],
    [
      1779052320000,
      "MEASURED",
      8,
      3.0
    ],
    [
      1779052500000,
      "MEASURED",
      8,
      3.0
    ],
    [
      1779052680000,
      "MEASURED",
      8,
      3.0
    ],
    [
      1779052860000,
      "MEASURED",
      8,
      3.0
    ],
    [
      1779053040000,
      "MEASURED",
      7,
      3.0
    ],
    [
      1779053220000,
      "MEASURED",
      7,
      3.0
    ],
    [
      1779053400000,
      "MEASURED",
      7,
      3.0
    ],
    [
      1779053580000,
      "MEASURED",
      7,
      3.0
    ],
    [
      1779053760000,
      "MEASURED",
      7,
      3.0
    ],
    [
      1779053940000,
      "MEASURED",
      7,
      3.0
    ],
    [
      1779054120000,
      "MEASURED",
      6,
      3.0
    ],
    [
      1779054300000,
      "MEASURED",
      6,
      3.0
    ],
    [
      1779054480000,
      "MEASURED",
      6,
      3.0
    ],
    [
      1779054660000,
      "MEASURED",
      6,
      3.0
    ],
    [
      1779054840000,
      "MEASURED",
      6,
      3.0
    ],
    [
      1779055020000,
      "MEASURED",
      6,
      3.0
    ],
    [
      1779055200000,
      "MEASURED",
      6,
      3.0
    ],
    [
      1779055380000,
      "MEASURED",
      6,
      3.0
    ],
    [
      1779055560000,
      "MEASURED",
      6,
      3.0
    ],
    [
      1779055740000,
      "MEASURED",
      6,
      3.0
    ],
    [
      1779055920000,
      "MEASURED",
      6,
      3.0
    ],
    [
      1779056100000,
      "MEASURED",
      6,
      3.0
    ],
    [
      1779056280000,
      "MEASURED",
      6,
      3.0
    ],
    [
      1779056460000,
      "MEASURED",
      6,
      3.0
    ],
    [
      1779056640000,
      "MEASURED",
      6,
      3.0
    ],
    [
      1779056820000,
      "MEASURED",
      6,
      3.0
    ],
    [
      1779057000000,
      "MEASURED",
      6,
      3.0
    ],
    [
      1779057180000,
      "MEASURED",
      6,
      3.0
    ],
    [
      1779057360000,
      "MEASURED",
      6,
      3.0
    ],
    [
      1779057540000,
      "MEASURED",
      6,
      3.0
    ],
    [
      1779057720000,
      "MEASURED",
      6,
      3.0
    ],
    [
      1779057900000,
      "MEASURED",
      6,
      3.0
    ],
    [
      1779058080000,
      "MEASURED",
      5,
      3.0
    ],
    [
      1779058260000,
      "MEASURED",
      5,
      3.0
    ],
    [
      1779058440000,
      "MEASURED",
      5,
      3.0
    ],
    [
      1779058620000,
      "MEASURED",
      5,
      3.0
    ],
    [
      1779058800000,
      "MEASURED",
      5,
      3.0
    ],
    [
      1779058980000,
      "MEASURED",
      5,
      3.0
    ],
    [
      1779059160000,
      "MEASURED",
      5,
      3.0
    ],
    [
      1779059340000,
      "MEASURED",
      5,
      3.0
    ],
    [
      1779059520000,
      "MEASURED",
      5,
      3.0
    ],
    [
      1779059700000,
      "MEASURED",
      5,
      3.0
    ],
    [
      1779059880000,
      "MEASURED",
      5,
      3.0
    ],
    [
      1779060060000,
      "MEASURED",
      5,
      3.0
    ],
    [
      1779060240000,
      "MEASURED",
      5,
      3.0
    ],
    [
      1779060420000,
      "MEASURED",
      5,
      3.0
    ],
    [
      1779060600000,
      "MEASURED",
      5,
      3.0
    ],
    [
      1779060780000,
      "MEASURED",
      5,
      3.0
    ],
    [
      1779060960000,
      "MEASURED",
      5,
      3.0
    ],
    [
      1779061140000,
      "MEASURED",
      5,
      3.0
    ],
    [
      1779061320000,
      "MEASURED",
      5,
      3.0
    ],
    [
      1779061500000,
      "MEASURED",
      5,
      3.0
    ],
    [
      1779061680000,
      "MEASURED",
      5,
      3.0
    ],
    [
      1779061860000,
      "MEASURED",
      5,
      3.0
    ],
    [
      1779062040000,
      "MEASURED",
      5,
      3.0
    ],
    [
      1779062220000,
      "MEASURED",
      5,
      3.0
    ],
    [
      1779062400000,
      "MEASURED",
      5,
      3.0
    ],
    [
      1779062580000,
      "MEASURED",
      5,
      3.0
    ],
    [
      1779062760000,
      "MEASURED",
      5,
      3.0
    ],
    [
      1779062940000,
      "MEASURED",
      5,
      3.0
    ],
    [
      1779063120000,
      "MEASURED",
      5,
      3.0
    ],
    [
      1779063300000,
      "MEASURED",
      5,
      3.0
    ],
    [
      1779063480000,
      "MEASURED",
      5,
      3.0
    ],
    [
      1779063660000,
      "MEASURED",
      5,
      3.0
    ],
    [
      1779063840000,
      "MEASURED",
      5,
      3.0
    ],
    [
      1779064020000,
      "MEASURED",
      5,
      3.0
    ],
    [
      1779064200000,
      "MEASURED",
      5,
      3.0
    ],
    [
      1779064380000,
      "MEASURED",
      5,
      3.0
    ],
    [
      1779064560000,
      "MEASURED",
      5,
      3.0
    ],
    [
      1779064740000,
      "MEASURED",
      5,
      3.0
    ],
    [
      1779064920000,
      "MEASURED",
      5,
      3.0
    ],
    [
      1779065100000,
      "MEASURED",
      5,
      3.0
    ],
    [
      1779065280000,
      "MEASURED",
      5,
      3.0
    ],
    [
      1779065460000,
      "MEASURED",
      5,
      3.0
    ],
    [
      1779065640000,
      "MEASURED",
      5,
      3.0
    ],
    [
      1779065820000,
      "MEASURED",
      5,
      3.0
    ],
    [
      1779066000000,
      "MEASURED",
      5,
      3.0
    ],
    [
      1779066180000,
      "MEASURED",
      5,
      3.0
    ],
    [
      1779066360000,
      "MEASURED",
      5,
      3.0
    ],
    [
      1779066540000,
      "MEASURED",
      5,
      3.0
    ],
    [
      1779066720000,
      "MEASURED",
      5,
      3.0
    ],
    [
      1779066900000,
      "MEASURED",
      5,
      3.0
    ],
    [
      1779067080000,
      "MEASURED",
      5,
      3.0
    ],
    [
      1779067260000,
      "MEASURED",
      5,
      3.0
    ],
    [
      1779067440000,
      "MEASURED",
      5,
      3.0
    ],
    [
      1779067620000,
      "MEASURED",
      5,
      3.0
    ],
    [
      1779067800000,
      "MEASURED",
      5,
      3.0
    ],
    [
      1779067980000,
      "MEASURED",
      5,
      3.0
    ],
    [
      1779068160000,
      "MEASURED",
      5,
      3.0
    ],
    [
      1779068340000,
      "MEASURED",
      5,
      3.0
    ],
    [
      1779068520000,
      "MEASURED",
      5,
      3.0
    ],
    [
      1779068700000,
      "MEASURED",
      5,
      3.0
    ],
    [
      1779068880000,
      "MEASURED",
      5,
      3.0
    ],
    [
      1779069060000,
      "MEASURED",
      5,
      3.0
    ],
    [
      1779069240000,
      "MEASURED",
      5,
      3.0
    ],
    [
      1779069420000,
      "MEASURED",
      5,
      3.0
    ],
    [
      1779069600000,
      "MEASURED",
      5,
      3.0
    ],
    [
      1779069780000,
      "MEASURED",
      5,
      3.0
    ],
    [
      1779069960000,
      "MEASURED",
      5,
      3.0
    ],
    [
      1779070140000,
      "MEASURED",
      5,
      3.0
    ],
    [
      1779070320000,
      "MEASURED",
      5,
      3.0
    ],
    [
      1779070500000,
      "MEASURED",
      5,
      3.0
    ],
    [
      1779070680000,
      "MEASURED",
      5,
      3.0
    ],
    [
      1779070860000,
      "MEASURED",
      5,
      3.0
    ],
    [
      1779071040000,
      "MEASURED",
      5,
      3.0
    ],
    [
      1779071220000,
      "MEASURED",
      6,
      3.0
    ],
    [
      1779071400000,
      "MEASURED",
      6,
      3.0
    ],
    [
      1779071580000,
      "MEASURED",
      6,
      3.0
    ],
    [
      1779071760000,
      "MEASURED",
      7,
      3.0
    ],
    [
      1779071940000,
      "MEASURED",
      7,
      3.0
    ],
    [
      1779072120000,
      "MEASURED",
      7,
      3.0
    ],
    [
      1779072300000,
      "MEASURED",
      8,
      3.0
    ],
    [
      1779072480000,
      "MEASURED",
      8,
      3.0
    ],
    [
      1779072660000,
      "MEASURED",
      8,
      3.0
    ],
    [
      1779072840000,
      "MEASURED",
      8,
      3.0
    ],
    [
      1779073020000,
      "MEASURED",
      9,
      3.0
    ]
  ]
}